Workbook
Name Dimensiones: [1]Listas!$A$2:$A$12
Name subsector: [1]Listas!$M$2:$M$5

Sheet Variable_indicador
A1: Descripción del indicador | L1: Metadato variable indicador | O1: Variable indicador
A2: Dimensión | B2: Codigo | C2: Nombre del indicador | D2: subsector | E2: Unidad de medida | F2: Periodicidad | G2: Cobertura geográfica | H2: Cobertura temporal | I2: Nombre de la Organización | J2: Nombre del cargo | K2: Fecha_entrega | L2: organismo | M2: año_vigencia | N2: Fuente | O2: Naturaleza del dato | P2: Tipo de dato variable | Q2: unidad | R2: Nombre de la variable | S2: Valor Variable
A3: Indique a que dimensión pertenece | C3: Indique el indicador que pertenece a la dimension | D3: Indique si es ( Energia, mineria, hidrocarburos o multisubsectorial) | F3: el indicador se mide por cual periodicidad | G3: alcance escala geografica | H3: año | I3: quien lo realizo | J3: escriba el nombre del profesional que esta a cargo de la metodologia del indicador | K3: fecha que descripcion metodologica del indicador | L3: entidad encargada de la variable del indicador | M3: fecha de publicacion de la variable | R3: Escriba el nombre de la variable del indicador | S3: Escriba el valor de la variable
A4: Normativa | B4: 1 | C4: 1.Reconocimiento y protección de los derechos ambientales en la política sectorial de derechos humanos | D4: Multisubsectorial | E4: Porcentaje (%) | F4: Anual | G4: Nacional | H4: 2023 | I4: Instituto de Estudios Ambientales -IDEA- | J4: Luis Fernando Sánchez Supelano | K4: 28 de marzo de 2025 | L4: Ministerio de minas y energia | M4: 2023 | N4: https://www.minenergia.gov.co/es/misional/gestión-social-y-ambiental/derechos-humanos/ | O4: Cuantitativo | P4: Entero (Integer int) | Q4: Numero de derechos | R4: 1.1.1. Número de derechos ambientales reconocidos en la política de derechos humanos del sector Minero Energético. | S4: 3
A5: Normativa | B5: 1 | C5: 1.Reconocimiento y protección de los derechos ambientales en la política sectorial de derechos humanos | D5: Multisubsectorial | E5: Porcentaje (%) | F5: Anual | G5: Nacional | H5: 2023 | I5: Instituto de Estudios Ambientales -IDEA- | J5: Luis Fernando Sánchez Supelano | K5: 28 de marzo de 2025 | L5: Ministerio de minas y energia | M5: 2023 | N5: https://www.minenergia.gov.co/es/misional/gestión-social-y-ambiental/derechos-humanos/ | O5: Cuantitativo | P5: Entero (Integer int) | Q5: Numero de derechos | R5: 1.1.2. Número total de derechos ambientales reconocidos en derechos internacionales | S5: 5
A6: Normativa | B6: 1 | C6: 1.Reconocimiento y protección de los derechos ambientales en la política sectorial de derechos humanos | D6: Multisubsectorial | E6: Porcentaje (%) | F6: Anual | G6: Nacional | H6: 2023 | I6: Instituto de Estudios Ambientales -IDEA- | J6: Luis Fernando Sánchez Supelano | K6: 28 de marzo de 2025 | L6: Ministerio de minas y energia | M6: 2023 | O6: Cuantitativo | P6: Flotante (Float Double) | Q6: Porcentaje | R6: 1.1.3.Puntuación reconocimiento formal derechos ambientales | S6: =S4/S5*100 -> 60
A7: Normativa | B7: 1 | C7: 1.Reconocimiento y protección de los derechos ambientales en la política sectorial de derechos humanos | D7: Multisubsectorial | E7: Porcentaje (%) | F7: Anual | G7: Nacional | H7: 2023 | I7: Instituto de Estudios Ambientales -IDEA- | J7: Luis Fernando Sánchez Supelano | K7: 28 de marzo de 2025 | L7: Ministerio de minas y energia | M7: 2023 | N7: https://www.minenergia.gov.co/es/misional/gestión-social-y-ambiental/derechos-humanos/ | O7: Cuantitativo | P7: Entero (Integer int) | Q7: Numero de derechos | R7: 1.2.1. Número de acciones para implementar la Política Sectoria pública de Derechos Humanos | S7: 0
A8: Normativa | B8: 1 | C8: 1.Reconocimiento y protección de los derechos ambientales en la política sectorial de derechos humanos | D8: Multisubsectorial | E8: Porcentaje (%) | F8: Anual | G8: Nacional | H8: 2023 | I8: Instituto de Estudios Ambientales -IDEA- | J8: Luis Fernando Sánchez Supelano | L8: Ministerio de minas y energia | M8: 2023 | N8: https://www.minenergia.gov.co/es/misional/gestión-social-y-ambiental/derechos-humanos/ | O8: Cuantitativo | P8: Entero (Integer int) | Q8: Numero de acciones | R8: 1.2.2.Acciones en específico para implementar la Política Sectoria pública de Derechos Humanos | S8: 0
A9: Normativa | B9: 1 | C9: 1.Reconocimiento y protección de los derechos ambientales en la política sectorial de derechos humanos | D9: Multisubsectorial | E9: Porcentaje (%) | F9: Anual | G9: Nacional | H9: 2023 | I9: Instituto de Estudios Ambientales -IDEA- | J9: Luis Fernando Sánchez Supelano | L9: Ministerio de minas y energia | M9: 2023 | O9: Cuantitativo | P9: Entero (Integer int) | Q9: Porcentaje | R9: 1.2.3. Puntuación plan de acción e implementación Política de derechos humanos | S9: 0
A10: Normativa | B10: 1 | C10: 1.Reconocimiento y protección de los derechos ambientales en la política sectorial de derechos humanos | D10: Multisubsectorial | E10: Porcentaje (%) | F10: Anual | G10: Nacional | H10: 2023 | I10: Instituto de Estudios Ambientales -IDEA- | J10: Luis Fernando Sánchez Supelano | K10: 28 de marzo de 2025 | L10: Ministerio de minas y energia | M10: 2023 | N10: https://www.minenergia.gov.co/es/ministerio/gestión/presupuesto/presupuesto-general-asignado/ | O10: Cualitativo | P10: Cadena de texto (String str). | R10: 1.3.1.Revisión asignaciones presupuestales | S10: Si
A11: Normativa | B11: 2 | C11: 2.Contexto favorable para el ejercicio de los derechos ambientales | D11: Multisubsectorial | E11: Porcentaje (%) | F11: Anual | G11: Nacional | H11: 2023 | I11: Instituto de Estudios Ambientales -IDEA- | M11: 2023 | N11: Observatorio OAAS | O11: Cualitativo | P11: Entero (Integer int) | Q11: numero de alertas | R11: 2.1.1.Número Total de alertas tempranas con seguimiento durante el año | S11: 8
A12: Normativa | B12: 2 | C12: 2.Contexto favorable para el ejercicio de los derechos ambientales | D12: Multisubsectorial | E12: Porcentaje (%) | F12: Anual | G12: Nacional | H12: 2023 | I12: Instituto de Estudios Ambientales -IDEA- | M12: 2023 | N12: Observatorio OAAS | O12: Cualitativo | P12: Entero (Integer int) | Q12: numero de alertas | R12: 2.1.2.Número Total de alertas tempranas durante el año | S12: 58
A13: Normativa | B13: 2 | C13: 2.Contexto favorable para el ejercicio de los derechos ambientales | D13: Multisubsectorial | E13: Porcentaje (%) | F13: Anual | G13: Nacional | H13: 2023 | I13: Instituto de Estudios Ambientales -IDEA- | M13: 2023 | N13: Observatorio OAAS | O13: Cuantitativo | P13: Booleano (Boolean bool) | Q13: puntaje | R13: 2.1.3.puntaje por Gestión frente alertas tempranas | S13: =S11/S12*100 -> 13.793103
A14: Normativa | B14: 2 | C14: 2.Contexto favorable para el ejercicio de los derechos ambientales | D14: Multisubsectorial | E14: Porcentaje (%) | F14: Anual | G14: Nacional | H14: 2023 | I14: Instituto de Estudios Ambientales -IDEA- | M14: 2023 | N14: Observatorio OAAS | O14: Cuantitativo | P14: Entero (Integer int) | Q14: numero de alertas | R14: 2.2.1 número Total de alertas tempranas con cierre durante el año | S14: 3
A15: Normativa | B15: 2 | C15: 2.Contexto favorable para el ejercicio de los derechos ambientales | D15: Multisubsectorial | E15: Porcentaje (%) | F15: Anual | G15: Nacional | H15: 2023 | I15: Instituto de Estudios Ambientales -IDEA- | M15: 2023 | N15: Observatorio OAAS | O15: Cuantitativo | P15: Flotante (Float Double) | Q15: puntaje | R15: 2.2.2.Puntaje por resultados frente alertas tempranas | S15: =S14/S12*100 -> 5.1724138
A16: Normativa | C16: 3.Analisis de impacto regulatorio con dimension ambiental | D16: Multisubsectorial | E16: Porcentaje (%) | F16: Anual | G16: Nacional | H16: 2023 | I16: Instituto de Estudios Ambientales -IDEA- | M16: 2023 | N16: https://www.minenergia.gov.co/es/servicio-al-ciudadano/foros/ | O16: Cuantitativo | P16: Entero (Integer int) | Q16: numero documentos | R16: 3.1.1.Numero de documentos que contienen analisis de variables ambientales | S16: 3
A17: Normativa | C17: 3.Analisis de impacto regulatorio con dimension ambiental | D17: Multisubsectorial | E17: Porcentaje (%) | F17: Anual | G17: Nacional | H17: 2023 | I17: Instituto de Estudios Ambientales -IDEA- | M17: 2023 | N17: https://www.minenergia.gov.co/es/servicio-al-ciudadano/foros/ | O17: Cuantitativo | P17: Entero (Integer int) | Q17: numero estudios de impacto normativo | R17: 3.1.2. Numero de estudios de impacto normativo realizados durante el año | S17: 4
A18: Normativa | C18: 3.Analisis de impacto regulatorio con dimension ambiental | D18: Multisubsectorial | E18: Porcentaje (%) | F18: Anual | G18: Nacional | H18: 2023 | I18: Instituto de Estudios Ambientales -IDEA- | M18: 2023 | O18: Cuantitativo | P18: Flotante (Float Double) | Q18: Porcentaje | R18: 3.1.3.AIN/Analisis de la variable ambiental | S18: =S16/S17*100 -> 75
A19: Normativa | C19: 4.Evaluación ex post de regulaciones | D19: Multisubsectorial | E19: Porcentaje (%) | F19: Anual | G19: Nacional | H19: 2023 | I19: Instituto de Estudios Ambientales -IDEA- | M19: 2023 | N19: https://www.minenergia.gov.co/es/servicio-al-ciudadano/foros/ | O19: Cualitativo | R19: 4.1.1.Consideración necesidad evaluación ex post | S19: Baja
A20: Normativa | C20: 4.Evaluación ex post de regulaciones | D20: Multisubsectorial | E20: Porcentaje (%) | F20: Anual | G20: Nacional | H20: 2023 | I20: Instituto de Estudios Ambientales -IDEA- | M20: 2023 | N20: https://www.minenergia.gov.co/es/servicio-al-ciudadano/foros/ | O20: Cuantitativo | Q20: numero Documentos que | R20: 4.2.1.Numero de Documentos que contiene la variable ambiental evaluación expost | S20: 0
A21: Normativa | C21: 4.Evaluación ex post de regulaciones | D21: Multisubsectorial | E21: Porcentaje (%) | F21: Anual | G21: Nacional | H21: 2023 | I21: Instituto de Estudios Ambientales -IDEA- | M21: 2023 | N21: https://www.minenergia.gov.co/es/servicio-al-ciudadano/foros/ | O21: Cuantitativo | Q21: numero Documentos de | R21: 4.2.1.Numero de Documentos de evaluación expost | S21: 2
A22: Normativa | C22: 4.Evaluación ex post de regulaciones | D22: Multisubsectorial | E22: Porcentaje (%) | F22: Anual | G22: Nacional | H22: 2023 | I22: Instituto de Estudios Ambientales -IDEA- | M22: 2023 | O22: Cuantitativo | P22: Flotante (Float Double) | Q22: nuntidad evaluaciones expost | R22: 4.2.3.Cantidad de evaluaciones expost que incorporaron el análisis de la variable ambiental | S22: =S20/S21*100 -> 0
A23: Normativa | C23: 5. Procesos de consulta publica en la producción Normativa | D23: Multisubsectorial | E23: Porcentaje (%) | F23: Anual | G23: Nacional | H23: 2023 | I23: Instituto de Estudios Ambientales -IDEA- | M23: 2023 | O23: Cuantitativo | Q23: nuumerodecretos sometidos | R23: 5.1.1. Numero de decretos sometidos a consultas | S23: 4
A24: Normativa | C24: 5. Procesos de consulta publica en la producción Normativa | D24: Multisubsectorial | E24: Porcentaje (%) | F24: Anual | G24: Nacional | H24: 2023 | I24: Instituto de Estudios Ambientales -IDEA- | M24: 2023 | O24: Cuantitativo | R24: 5.1.2 Numero de decretos | S24: 5
A25: Normativa | C25: 5. Procesos de consulta publica en la producción Normativa | D25: Multisubsectorial | E25: Porcentaje (%) | F25: Anual | G25: Nacional | H25: 2023 | I25: Instituto de Estudios Ambientales -IDEA- | M25: 2023 | O25: Cuantitativo | Q25: nuormulen consulta | R25: 5.1.3. Formula dcretos en consulta/N decretos | S25: =S23/S24*100 -> 80
A26: Analisis Institucional | C26: 6. Puntaje del sector de minas y energia en el indice de desempeño Institucional | D26: Multisubsectorial | E26: Porcentaje (%) | F26: Anual | G26: Nacional | H26: 2023 | I26: Instituto de Estudios Ambientales -IDEA- | M26: 2023 | O26: Cuantitativo | Q26: nuromedio obtenido en el en el | R26: 6.1.1. promedio obtenido en el sector de minas y energia del resultado desempeño institucional | S26: 82.4 | T26: 88.6
A27: Analisis Institucional | C27: 6. Puntaje del sector de minas y energia en el indice de desempeño Institucional | D27: Multisubsectorial | E27: Porcentaje (%) | F27: Anual | G27: Nacional | H27: 2023 | I27: Instituto de Estudios Ambientales -IDEA- | M27: 2023 | O27: Cuantitativo | Q27: nuntaje al índice | R27: 6.1.2.Puntaje correspondiente al índice de gobernanza | S27: 21
A28: Analisis Institucional | C28: 6. Puntaje del sector de minas y energia en el indice de desempeño Institucional | D28: Multisubsectorial | E28: Porcentaje (%) | F28: Anual | G28: Nacional | H28: 2023 | I28: Instituto de Estudios Ambientales -IDEA- | M28: 2023 | O28: Cuantitativo | Q28: nuntaje en el | R28: 6.1.3.Puntaje obtenido en el Índice de desempeño instituciona | S28: 100
A29: Analisis Institucional | C29: 6. Puntaje del sector de minas y energia en el indice de desempeño Institucional | D29: Multisubsectorial | E29: Porcentaje (%) | F29: Anual | G29: Nacional | H29: 2023 | I29: Instituto de Estudios Ambientales -IDEA- | M29: 2023 | O29: Cuantitativo | Q29: nuntaje en el | R29: 6.1.4.Puntaje obtenido en el año de referencia en el IDI (POIDI) | S29: =S26*S27/S28 -> 17.304
A30: Analisis Institucional | C30: 7. Coordinación interinstitucional | D30: Multisubsectorial | E30: Porcentaje (%) | F30: Anual | G30: Nacional | H30: 2023 | I30: Instituto de Estudios Ambientales -IDEA- | M30: 2023 | O30: Cuantitativo | Q30: nuntuación y funcionamiento | R30: 7.1.1.Puntuación existencia y funcionamiento mecanismos coordinación | S30: Alto
A31: Analisis Institucional | C31: 7. Coordinación interinstitucional | D31: Multisubsectorial | E31: Porcentaje (%) | F31: Anual | G31: Nacional | H31: 2023 | I31: Instituto de Estudios Ambientales -IDEA- | M31: 2023 | O31: Cuantitativo | R31: 7.1.2.Nivel de cumplimiento de los instrumentos de coordinación interinstitucional a través de a) derecho de petición a la Oficina de Asuntos Ambientales y Sociales del Ministerio de Minas y Energía, b) revisiones informes de rendición de cuentas, c) informes de seguimiento a los planes formulados en el contexto de los mecanismos de coordinación interinstitucional | S31: 0
A32: Analisis Institucional | C32: 8. Acceso a la justicia | D32: Multisubsectorial | E32: Porcentaje (%) | F32: Anual | G32: Nacional | H32: 2023 | I32: Instituto de Estudios Ambientales -IDEA- | M32: 2023 | O32: Cuantitativo | Q32: nuumero de ordenes que no registran acciones pendientes ordenes que | R32: 8.1.1. Numero de ordenes que no registran acciones pendientes de realizar y por tanto se entienden como cumplidas | S32: 4
A33: Analisis Institucional | C33: 8. Acceso a la justicia | D33: Multisubsectorial | E33: Porcentaje (%) | F33: Anual | G33: Nacional | H33: 2023 | I33: Instituto de Estudios Ambientales -IDEA- | M33: 2023 | O33: Cuantitativo | Q33: nuumero de procesos judiciales con procesos judiciales | R33: 8.1.2. Numero de procesos judiciales con órdenes directas para el Ministerio de Minas y Energía | S33: 27
A34: Analisis Institucional | C34: 8. Acceso a la justicia | D34: Multisubsectorial | E34: Porcentaje (%) | F34: Anual | G34: Nacional | H34: 2023 | I34: Instituto de Estudios Ambientales -IDEA- | M34: 2023 | O34: Cuantitativo | Q34: nuormula relacion que se entienden que se | R34: 8.1.3. Formula relacion que se entienden como cumplidas y numero de procesos directos del MME | S34: =S32/S33*100 -> 14.814815
A35: Sociales | C35: 9. Participación ciudadana | D35: Multisubsectorial | E35: Porcentaje (%) | F35: Anual | G35: Nacional | H35: 2023 | I35: Instituto de Estudios Ambientales -IDEA- | M35: 2023 | O35: Cuantitativo | P35: Entero (Integer int) | Q35: numatoria evento asistencia | R35: 9.1.1.sumatoria asistencia evento asistencia Informativo | S35: 17036
A36: Sociales | C36: 9. Participación ciudadana | D36: Multisubsectorial | E36: Porcentaje (%) | F36: Anual | G36: Nacional | H36: 2023 | I36: Instituto de Estudios Ambientales -IDEA- | M36: 2023 | O36: Cuantitativo | P36: Entero (Integer int) | Q36: nuumatoevento Toma | R36: 9.1.2. sumatoria asistencia evento Toma de Decisiones Participativas | S36: 7683
A37: Sociales | C37: 9. Participación ciudadana | D37: Multisubsectorial | E37: Porcentaje (%) | F37: Anual | G37: Nacional | H37: 2023 | I37: Instituto de Estudios Ambientales -IDEA- | M37: 2023 | O37: Cuantitativo | P37: Entero (Integer int) | Q37: numatoria evento Pedagógico | R37: 9.1.3.sumatoria asistencia evento Pedagógico | S37: 9657
A38: Sociales | C38: 9. Participación ciudadana | D38: Multisubsectorial | E38: Porcentaje (%) | F38: Anual | G38: Nacional | H38: 2023 | I38: Instituto de Estudios Ambientales -IDEA- | M38: 2023 | O38: Cuantitativo | P38: Entero (Integer int) | Q38: numatoria evento Planeación | R38: 9.1.4.sumatoria asistencia evento Planeación Participativa | S38: 12447
A39: Sociales | C39: 9. Participación ciudadana | D39: Multisubsectorial | E39: Porcentaje (%) | F39: Anual | G39: Nacional | H39: 2023 | I39: Instituto de Estudios Ambientales -IDEA- | M39: 2023 | O39: Cuantitativo | P39: Entero (Integer int) | Q39: nusolución Conflicto | R39: 9.1.5.Resolución de Conflictos | S39: 579
A40: Sociales | C40: 9. Participación ciudadana | D40: Multisubsectorial | E40: Porcentaje (%) | F40: Anual | G40: Nacional | H40: 2023 | I40: Instituto de Estudios Ambientales -IDEA- | M40: 2023 | O40: Cuantitativo | P40: Entero (Integer int) | R40: 91.6. Sumatorio asistentes | S40: =SUM(S35:S39) -> 47402
A41: Sociales | C41: 9. Participación ciudadana | D41: Multisubsectorial | E41: Porcentaje (%) | F41: Anual | G41: Nacional | H41: 2023 | I41: Instituto de Estudios Ambientales -IDEA- | M41: 2023 | O41: Cuantitativo | P41: Flotante (Float Double) | R41: 9.2.1. Informativo | S41: 0.7
A42: Sociales | C42: 9. Participación ciudadana | D42: Multisubsectorial | E42: Porcentaje (%) | F42: Anual | G42: Nacional | H42: 2023 | I42: Instituto de Estudios Ambientales -IDEA- | M42: 2023 | O42: Cuantitativo | P42: Flotante (Float Double) | Q42: numa Decisiones Participativas | R42: 9.2.2.Toma de Decisiones Participativas | S42: 1
A43: Sociales | C43: 9. Participación ciudadana | D43: Multisubsectorial | E43: Porcentaje (%) | F43: Anual | G43: Nacional | H43: 2023 | I43: Instituto de Estudios Ambientales -IDEA- | M43: 2023 | O43: Cuantitativo | P43: Flotante (Float Double) | R43: 9.2.3.Pedagógico | S43: 0.8
A44: Sociales | C44: 9. Participación ciudadana | D44: Multisubsectorial | E44: Porcentaje (%) | F44: Anual | G44: Nacional | H44: 2023 | I44: Instituto de Estudios Ambientales -IDEA- | M44: 2023 | O44: Cuantitativo | P44: Flotante (Float Double) | Q44: nuaneación rticipativ | R44: 9.2.4.Planeación Participativa | S44: 1
A45: Sociales | C45: 9. Participación ciudadana | D45: Multisubsectorial | E45: Porcentaje (%) | F45: Anual | G45: Nacional | H45: 2023 | I45: Instituto de Estudios Ambientales -IDEA- | M45: 2023 | O45: Cuantitativo | P45: Flotante (Float Double) | Q45: nusolución Conflicto | R45: 9.2.5.Resolución de Conflictos | S45: 0.8
A46: Sociales | C46: 10. Interacción de género y enfoque diferencial | D46: Multisubsectorial | E46: Porcentaje (%) | F46: Anual | G46: Nacional | H46: 2023 | I46: Instituto de Estudios Ambientales -IDEA- | M46: 2023 | O46: Cuantitativo | P46: Entero (Integer int) | R46: 10.1.1.Mujeres 2022 | S46: 45
A47: Sociales | C47: 10. Interacción de género y enfoque diferencial | D47: Multisubsectorial | E47: Porcentaje (%) | F47: Anual | G47: Nacional | H47: 2023 | I47: Instituto de Estudios Ambientales -IDEA- | M47: 2023 | O47: Cuantitativo | P47: Entero (Integer int) | R47: 10.1.2.Adulto mayor 2022 | S47: 28
A48: Sociales | C48: 10. Interacción de género y enfoque diferencial | D48: Multisubsectorial | E48: Porcentaje (%) | F48: Anual | G48: Nacional | H48: 2023 | I48: Instituto de Estudios Ambientales -IDEA- | M48: 2023 | O48: Cuantitativo | P48: Entero (Integer int) | Q48: nuoblación discapacidad 2022 | R48: 10.1.3.Población con discapacidad 2022 | S48: 8
A49: Sociales | C49: 10. Interacción de género y enfoque diferencial | D49: Multisubsectorial | E49: Porcentaje (%) | F49: Anual | G49: Nacional | H49: 2023 | I49: Instituto de Estudios Ambientales -IDEA- | M49: 2023 | O49: Cuantitativo | P49: Entero (Integer int) | R49: 10.1.4.Grupos étnicos 2022 | S49: 5.95
A50: Sociales | C50: 10. Interacción de género y enfoque diferencial | D50: Multisubsectorial | E50: Porcentaje (%) | F50: Anual | G50: Nacional | H50: 2023 | I50: Instituto de Estudios Ambientales -IDEA- | M50: 2023 | O50: Cuantitativo | P50: Entero (Integer int) | R50: 10.1.5.Desplazados 2022 | S50: 10
A51: Sociales | C51: 10. Interacción de género y enfoque diferencial | D51: Multisubsectorial | E51: Porcentaje (%) | F51: Anual | G51: Nacional | H51: 2023 | I51: Instituto de Estudios Ambientales -IDEA- | M51: 2023 | O51: Cuantitativo | P51: Entero (Integer int) | Q51: nuíctimas conflicto armado | R51: 10.1.6.Víctimas del conflicto armado 2022 | S51: 13
A52: Sociales | C52: 10. Interacción de género y enfoque diferencial | D52: Multisubsectorial | E52: Porcentaje (%) | F52: Anual | G52: Nacional | H52: 2023 | I52: Instituto de Estudios Ambientales -IDEA- | M52: 2023 | O52: Cuantitativo | P52: Entero (Integer int) | Q52: nunteracción 2022 | R52: 10.1.7.Interacción anual 2022 | S52: =S46+S47+S48+S50+S51 -> 104
A53: Sociales | C53: 10. Interacción de género y enfoque diferencial | D53: Multisubsectorial | E53: Porcentaje (%) | F53: Anual | G53: Nacional | H53: 2023 | I53: Instituto de Estudios Ambientales -IDEA- | M53: 2023 | O53: Cuantitativo | P53: Entero (Integer int) | R53: 10.2.1.Mujeres 2023 | S53: 50
A54: Sociales | C54: 10. Interacción de género y enfoque diferencial | D54: Multisubsectorial | E54: Porcentaje (%) | F54: Anual | G54: Nacional | H54: 2023 | I54: Instituto de Estudios Ambientales -IDEA- | M54: 2023 | O54: Cuantitativo | P54: Entero (Integer int) | R54: 10.2.2.Adulto mayor 2023 | S54: 21
A55: Sociales | C55: 10. Interacción de género y enfoque diferencial | D55: Multisubsectorial | E55: Porcentaje (%) | F55: Anual | G55: Nacional | H55: 2023 | I55: Instituto de Estudios Ambientales -IDEA- | M55: 2023 | O55: Cuantitativo | P55: Entero (Integer int) | Q55: nuoblación discapacidad 2022 | R55: 10.2.3.Población con discapacidad 2022 | S55: 6
A56: Sociales | C56: 10. Interacción de género y enfoque diferencial | D56: Multisubsectorial | E56: Porcentaje (%) | F56: Anual | G56: Nacional | H56: 2023 | I56: Instituto de Estudios Ambientales -IDEA- | M56: 2023 | O56: Cuantitativo | P56: Entero (Integer int) | R56: 10.2.4.Grupos étnicos 2023 | S56: 14.79
A57: Sociales | C57: 10. Interacción de género y enfoque diferencial | D57: Multisubsectorial | E57: Porcentaje (%) | F57: Anual | G57: Nacional | H57: 2023 | I57: Instituto de Estudios Ambientales -IDEA- | M57: 2023 | O57: Cuantitativo | P57: Entero (Integer int) | R57: 10.2.5.Desplazados 2023 | S57: 8
A58: Sociales | C58: 10. Interacción de género y enfoque diferencial | D58: Multisubsectorial | E58: Porcentaje (%) | F58: Anual | G58: Nacional | H58: 2023 | I58: Instituto de Estudios Ambientales -IDEA- | M58: 2023 | O58: Cuantitativo | P58: Entero (Integer int) | Q58: nuíctimas conflicto armado | R58: 10.2.6.Víctimas del conflicto armado 2023 | S58: 30
A59: Sociales | C59: 10. Interacción de género y enfoque diferencial | D59: Multisubsectorial | E59: Porcentaje (%) | F59: Anual | G59: Nacional | H59: 2023 | I59: Instituto de Estudios Ambientales -IDEA- | M59: 2023 | O59: Cuantitativo | P59: Entero (Integer int) | Q59: nunteracción 2023 | R59: 10.2.7.Interacción anual 2023 | S59: =S53+S54+S55+S57+S58 -> 115
A60: Sociales | C60: 10. Interacción de género y enfoque diferencial | D60: Multisubsectorial | E60: Porcentaje (%) | F60: Anual | G60: Nacional | H60: 2023 | I60: Instituto de Estudios Ambientales -IDEA- | M60: 2023 | O60: Cuantitativo | R60: 10.3.1. %Mujeres 2022 | S60: =S46*100/$S$52 -> 43.269231
A61: Sociales | C61: 10. Interacción de género y enfoque diferencial | D61: Multisubsectorial | E61: Porcentaje (%) | F61: Anual | G61: Nacional | H61: 2023 | I61: Instituto de Estudios Ambientales -IDEA- | M61: 2023 | O61: Cuantitativo | R61: 10.3.2.%Adulto mayor 2022 | S61: =S47*100/$S$52 -> 26.923077
A62: Sociales | C62: 10. Interacción de género y enfoque diferencial | D62: Multisubsectorial | E62: Porcentaje (%) | F62: Anual | G62: Nacional | H62: 2023 | I62: Instituto de Estudios Ambientales -IDEA- | M62: 2023 | O62: Cuantitativo | Q62: nuPoblación discapacidad 2022 | R62: 10.3.3.%Población con discapacidad 2022 | S62: =S48*100/$S$52 -> 7.6923077
A63: Sociales | C63: 10. Interacción de género y enfoque diferencial | D63: Multisubsectorial | E63: Porcentaje (%) | F63: Anual | G63: Nacional | H63: 2023 | I63: Instituto de Estudios Ambientales -IDEA- | M63: 2023 | O63: Cuantitativo | R63: 10.3.4.%Grupos étnicos 2022 | S63: =S49 -> 5.95
A64: Sociales | C64: 10. Interacción de género y enfoque diferencial | D64: Multisubsectorial | E64: Porcentaje (%) | F64: Anual | G64: Nacional | H64: 2023 | I64: Instituto de Estudios Ambientales -IDEA- | M64: 2023 | O64: Cuantitativo | R64: 10.3.5. %Desplazados 2022 | S64: =S50*100/$S$52 -> 9.6153846
A65: Sociales | C65: 10. Interacción de género y enfoque diferencial | D65: Multisubsectorial | E65: Porcentaje (%) | F65: Anual | G65: Nacional | H65: 2023 | I65: Instituto de Estudios Ambientales -IDEA- | M65: 2023 | O65: Cuantitativo | Q65: nuVíctimas conflicto armado | R65: 10.3.6.%Víctimas del conflicto armado 2022 | S65: =S51*100/$S$52 -> 12.5
A66: Sociales | C66: 10. Interacción de género y enfoque diferencial | D66: Multisubsectorial | E66: Porcentaje (%) | F66: Anual | G66: Nacional | H66: 2023 | I66: Instituto de Estudios Ambientales -IDEA- | M66: 2023 | O66: Cuantitativo | R66: 10.4.1.%Mujeres 4043 | S66: =S53*100/$S$59 -> 43.478261
A67: Sociales | C67: 10. Interacción de género y enfoque diferencial | D67: Multisubsectorial | E67: Porcentaje (%) | F67: Anual | G67: Nacional | H67: 2023 | I67: Instituto de Estudios Ambientales -IDEA- | M67: 2023 | O67: Cuantitativo | R67: 10.4.2.%Adulto mayor 4043 | S67: =S54*100/$S$59 -> 18.26087
A68: Sociales | C68: 10. Interacción de género y enfoque diferencial | D68: Multisubsectorial | E68: Porcentaje (%) | F68: Anual | G68: Nacional | H68: 2023 | I68: Instituto de Estudios Ambientales -IDEA- | M68: 2023 | O68: Cuantitativo | Q68: nuPoblación discapacidad 4044 | R68: 10.4.3.%Población con discapacidad 4044 | S68: =S55*100/$S$59 -> 5.2173913
A69: Sociales | C69: 10. Interacción de género y enfoque diferencial | D69: Multisubsectorial | E69: Porcentaje (%) | F69: Anual | G69: Nacional | H69: 2023 | I69: Instituto de Estudios Ambientales -IDEA- | M69: 2023 | O69: Cuantitativo | R69: 10.4.4.%Grupos étnicos 4043 | S69: =S56 -> 14.79
A70: Sociales | C70: 10. Interacción de género y enfoque diferencial | D70: Multisubsectorial | E70: Porcentaje (%) | F70: Anual | G70: Nacional | H70: 2023 | I70: Instituto de Estudios Ambientales -IDEA- | M70: 2023 | O70: Cuantitativo | R70: 10.4.5.%Desplazados 4043 | S70: =S57*100/$S$59 -> 6.9565217
A71: Sociales | C71: 10. Interacción de género y enfoque diferencial | D71: Multisubsectorial | E71: Porcentaje (%) | F71: Anual | G71: Nacional | H71: 2023 | I71: Instituto de Estudios Ambientales -IDEA- | M71: 2023 | O71: Cuantitativo | Q71: nuVíctimas conflicto armado | R71: 10.4.6.%Víctimas del conflicto armado 4043 | S71: =S58*100/$S$59 -> 26.086957
A72: Sociales | C72: 10. Interacción de género y enfoque diferencial | D72: Multisubsectorial | E72: Porcentaje (%) | F72: Anual | G72: Nacional | H72: 2023 | I72: Instituto de Estudios Ambientales -IDEA- | M72: 2023 | O72: Cuantitativo | Q72: nu_xDC3C_𝑛𝑡𝑒𝑟𝑎𝑐𝑐𝑖ó𝑛 𝑐𝑎𝑏𝑒𝑧𝑎 𝑑𝑒 | R72: 10.5.1.𝐼𝑛𝑡𝑒𝑟𝑎𝑐𝑐𝑖ó𝑛 𝑚𝑢𝑗𝑒𝑟𝑒𝑠 𝑐𝑎𝑏𝑒𝑧𝑎 𝑑𝑒 𝑓𝑎𝑚𝑖𝑙𝑖𝑎 | S72: =((S66-S60)/S60)*100 -> 0.48309179
A73: Sociales | C73: 10. Interacción de género y enfoque diferencial | D73: Multisubsectorial | E73: Porcentaje (%) | F73: Anual | G73: Nacional | H73: 2023 | I73: Instituto de Estudios Ambientales -IDEA- | M73: 2023 | O73: Cuantitativo | Q73: nu_xDC4E_𝑐𝑐𝑖ó𝑛 | R73: 10.5.2. 𝐼𝑛𝑡𝑒𝑟𝑎𝑐𝑐𝑖ó𝑛 𝑎𝑑𝑢𝑙𝑡𝑜 𝑚𝑎𝑦𝑜𝑟 | S73: =((S67-S61)/S61)*100 -> -32.173913
A74: Sociales | C74: 10. Interacción de género y enfoque diferencial | D74: Multisubsectorial | E74: Porcentaje (%) | F74: Anual | G74: Nacional | H74: 2023 | I74: Instituto de Estudios Ambientales -IDEA- | M74: 2023 | O74: Cuantitativo | Q74: nu_xDC3C_𝑛𝑡𝑒𝑟𝑎𝑐𝑐𝑖ó𝑛 𝑐𝑜𝑛 𝑑𝑖𝑠𝑐𝑎𝑝𝑎𝑐𝑖𝑑𝑎𝑑 | R74: 10.5.3.𝐼𝑛𝑡𝑒𝑟𝑎𝑐𝑐𝑖ó𝑛 𝑝𝑜𝑏𝑙𝑎𝑐𝑖ó𝑛 𝑐𝑜𝑛 𝑑𝑖𝑠𝑐𝑎𝑝𝑎𝑐𝑖𝑑𝑎𝑑 | S74: =((S68-S62)/S62)*100 -> -32.173913
A75: Sociales | C75: 10. Interacción de género y enfoque diferencial | D75: Multisubsectorial | E75: Porcentaje (%) | F75: Anual | G75: Nacional | H75: 2023 | I75: Instituto de Estudios Ambientales -IDEA- | M75: 2023 | O75: Cuantitativo | Q75: nu_xDC4E_𝑐𝑐𝑖ó𝑛 | R75: 10.5.4. 𝐼𝑛𝑡𝑒𝑟𝑎𝑐𝑐𝑖ó𝑛 𝑔𝑟𝑢𝑝𝑜 é𝑡𝑛𝑖𝑐𝑜 | S75: =((S69-S63)/S63)*100 -> 148.57143
A76: Sociales | C76: 10. Interacción de género y enfoque diferencial | D76: Multisubsectorial | E76: Porcentaje (%) | F76: Anual | G76: Nacional | H76: 2023 | I76: Instituto de Estudios Ambientales -IDEA- | M76: 2023 | O76: Cuantitativo | Q76: nu_xDC3C_𝑛𝑡𝑒𝑟𝑎𝑐𝑐𝑖ó𝑛 𝑐𝑐𝑖ó𝑛 | R76: 10.5.5.𝐼𝑛𝑡𝑒𝑟𝑎𝑐𝑐𝑖ó𝑛 𝑑𝑒𝑠𝑝𝑙𝑎𝑧𝑎𝑑𝑜𝑠 | S76: =((S70-S64)/S64)*100 -> -27.652174
A77: Sociales | C77: 10. Interacción de género y enfoque diferencial | D77: Multisubsectorial | E77: Porcentaje (%) | F77: Anual | G77: Nacional | H77: 2023 | I77: Instituto de Estudios Ambientales -IDEA- | M77: 2023 | O77: Cuantitativo | Q77: nu_xDC3C_𝑛𝑡𝑒𝑟𝑎𝑐𝑐𝑖ó𝑛 𝑑𝑒𝑙 𝑐𝑜𝑛𝑓𝑙𝑖𝑐𝑡𝑜 | R77: 10.5.6.𝐼𝑛𝑡𝑒𝑟𝑎𝑐𝑐𝑖ó𝑛 𝑣í𝑐𝑡𝑖𝑚𝑎𝑠 𝑑𝑒𝑙 𝑐𝑜𝑛𝑓𝑙𝑖𝑐𝑡𝑜 | S77: =((S71-S65)/S65)*100 -> 108.69565
A78: Sociales | C78: 11. Conflictividad socioambiental | D78: Multisubsectorial | E78: Porcentaje (%) | F78: Anual | G78: Nacional | H78: 2023 | I78: Instituto de Estudios Ambientales -IDEA- | M78: 2023 | O78: Cuantitativo | P78: Entero (Integer int) | R78: 11.1. Conflictos sociales | S78: 8
A79: Sociales | C79: 11. Conflictividad socioambiental | D79: Multisubsectorial | E79: Porcentaje (%) | F79: Anual | G79: Nacional | H79: 2023 | I79: Instituto de Estudios Ambientales -IDEA- | M79: 2023 | O79: Cuantitativo | P79: Entero (Integer int) | R79: 11.2. Conflictos ambientales | S79: 25
A80: Sociales | C80: 11. Conflictividad socioambiental | D80: Multisubsectorial | E80: Porcentaje (%) | F80: Anual | G80: Nacional | H80: 2023 | I80: Instituto de Estudios Ambientales -IDEA- | M80: 2023 | O80: Cuantitativo | P80: Entero (Integer int) | R80: 11.3. Conflictos compartidos | S80: 16
A81: Sociales | C81: 11. Conflictividad socioambiental | D81: Multisubsectorial | E81: Porcentaje (%) | F81: Anual | G81: Nacional | H81: 2023 | I81: Instituto de Estudios Ambientales -IDEA- | M81: 2023 | O81: Cuantitativo | P81: Entero (Integer int) | Q81: nual sociales ambientales | R81: 11.4.Total conflictos sociales ambientales | S81: 49
A82: Sociales | C82: 11. Conflictividad socioambiental | D82: Multisubsectorial | E82: Porcentaje (%) | F82: Anual | G82: Nacional | H82: 2023 | I82: Instituto de Estudios Ambientales -IDEA- | M82: 2023 | O82: Cuantitativo | P82: Entero (Integer int) | Q82: nutal cdentro de | R82: 11.5. Total conflictos dentro de la matriz | S82: 139
A83: Sociales | C83: 12. Cumplimiento a PQRSD | D83: Multisubsectorial | E83: Porcentaje (%) | F83: Anual | G83: Nacional | H83: 2023 | I83: Instituto de Estudios Ambientales -IDEA- | M83: 2023 | O83: Cuantitativo | P83: Entero (Integer int) | Q83: nuPQRS atendidas | R83: 12.1.1. Porcentaje de PQRS atendidas I informe 2023 | S83: 90.49
A84: Sociales | C84: 12. Cumplimiento a PQRSD | D84: Multisubsectorial | E84: Porcentaje (%) | F84: Anual | G84: Nacional | H84: 2023 | I84: Instituto de Estudios Ambientales -IDEA- | M84: 2023 | O84: Cuantitativo | P84: Entero (Integer int) | Q84: nuPQRS atendidas | R84: 12.1.2. Porcentaje de PQRS atendidas II informe 2023 | S84: 95.71
A85: Sociales | C85: 12. Cumplimiento a PQRSD | D85: Multisubsectorial | E85: Porcentaje (%) | F85: Anual | G85: Nacional | H85: 2023 | I85: Instituto de Estudios Ambientales -IDEA- | M85: 2023 | O85: Cuantitativo | P85: Entero (Integer int) | Q85: nuPQRS atendidas | R85: 12.1.3. Porcentaje de PQRS atendidas II informe 2023 | S85: 95.54
A86: Sociales | C86: 12. Cumplimiento a PQRSD | D86: Multisubsectorial | E86: Porcentaje (%) | F86: Anual | G86: Nacional | H86: 2023 | I86: Instituto de Estudios Ambientales -IDEA- | M86: 2023 | O86: Cuantitativo | P86: Entero (Integer int) | Q86: nuPQRS atendidas | R86: 12.1.4. Porcentaje de PQRS atendidas IV informe 2023 | S86: 95.51
A87: Biofisica y ecologica | C87: 13.Variación de la demanda hídrica | D87: Multisubsectorial | E87: Porcentaje (%) | F87: Anual | G87: Nacional | H87: 2023 | I87: Instituto de Estudios Ambientales -IDEA- | M87: 2023 | O87: Cuantitativo | Q87: nudel Agua | R87: 13.1.1. Estudio Nacional del Agua Energia 2012 | S87: 7740.3
A88: Biofisica y ecologica | C88: 13.Variación de la demanda hídrica | D88: Multisubsectorial | E88: Porcentaje (%) | F88: Anual | G88: Nacional | H88: 2023 | I88: Instituto de Estudios Ambientales -IDEA- | M88: 2023 | O88: Cuantitativo | Q88: nudel Agua | R88: 13.1.2. Estudio Nacional del Agua Mineria 2012 | S88: 2106
A89: Biofisica y ecologica | C89: 13.Variación de la demanda hídrica | D89: Multisubsectorial | E89: Porcentaje (%) | F89: Anual | G89: Nacional | H89: 2023 | I89: Instituto de Estudios Ambientales -IDEA- | M89: 2023 | O89: Cuantitativo | Q89: nudel Agua | R89: 13.1.3. Estudio Nacional del Agua Hidrocarburos 2012 | S89: 640.6
A90: Biofisica y ecologica | C90: 13.Variación de la demanda hídrica | D90: Multisubsectorial | E90: Porcentaje (%) | F90: Anual | G90: Nacional | H90: 2023 | I90: Instituto de Estudios Ambientales -IDEA- | M90: 2023 | O90: Cuantitativo | Q90: nudel Agua | R90: 13.1.1. Estudio Nacional del Agua Energia 2016 | S90: 9069.5
A91: Biofisica y ecologica | C91: 13.Variación de la demanda hídrica | D91: Multisubsectorial | E91: Porcentaje (%) | F91: Anual | G91: Nacional | H91: 2023 | I91: Instituto de Estudios Ambientales -IDEA- | M91: 2023 | O91: Cuantitativo | Q91: nudel Agua | R91: 13.1.2. Estudio Nacional del Agua Mineria 2016 | S91: 1074.6
A92: Biofisica y ecologica | C92: 13.Variación de la demanda hídrica | D92: Multisubsectorial | E92: Porcentaje (%) | F92: Anual | G92: Nacional | H92: 2023 | I92: Instituto de Estudios Ambientales -IDEA- | M92: 2023 | O92: Cuantitativo | Q92: nudel Agua | R92: 13.1.3. Estudio Nacional del Agua Hidrocarburos 2016 | S92: 668.2
A93: Biofisica y ecologica | C93: 13.Variación de la demanda hídrica | D93: Multisubsectorial | E93: Porcentaje (%) | F93: Anual | G93: Nacional | H93: 2023 | I93: Instituto de Estudios Ambientales -IDEA- | M93: 2023 | O93: Cuantitativo | Q93: nudel Agua | R93: 13.1.1. Estudio Nacional del Agua Energia 2020 | S93: 8224.4
A94: Biofisica y ecologica | C94: 13.Variación de la demanda hídrica | D94: Multisubsectorial | E94: Porcentaje (%) | F94: Anual | G94: Nacional | H94: 2023 | I94: Instituto de Estudios Ambientales -IDEA- | M94: 2023 | O94: Cuantitativo | Q94: nudel Agua | R94: 13.1.2. Estudio Nacional del Agua Mineria 2020 | S94: 660.9
A95: Biofisica y ecologica | C95: 13.Variación de la demanda hídrica | D95: Multisubsectorial | E95: Porcentaje (%) | F95: Anual | G95: Nacional | H95: 2023 | I95: Instituto de Estudios Ambientales -IDEA- | M95: 2023 | O95: Cuantitativo | Q95: nudel Agua | R95: 13.1.3. Estudio Nacional del Agua Hidrocarburos 2020 | S95: 419.5
A96: Biofisica y ecologica | C96: 13.Variación de la demanda hídrica | D96: Multisubsectorial | E96: Porcentaje (%) | F96: Anual | G96: Nacional | H96: 2023 | I96: Instituto de Estudios Ambientales -IDEA- | M96: 2023 | O96: Cuantitativo | R96: 13.2.1. Energia 2012-2016 | S96: =S87-S90 -> -1329.2
A97: Biofisica y ecologica | C97: 13.Variación de la demanda hídrica | D97: Multisubsectorial | E97: Porcentaje (%) | F97: Anual | G97: Nacional | H97: 2023 | I97: Instituto de Estudios Ambientales -IDEA- | M97: 2023 | O97: Cuantitativo | R97: 13.2.2. Mineria 2012-2016 | S97: =S88-S91 -> 1031.4
A98: Biofisica y ecologica | C98: 13.Variación de la demanda hídrica | D98: Multisubsectorial | E98: Porcentaje (%) | F98: Anual | G98: Nacional | H98: 2023 | I98: Instituto de Estudios Ambientales -IDEA- | M98: 2023 | O98: Cuantitativo | Q98: nu20 | R98: 13.2.3. Hidrocarburos 2012-2016 | S98: =S89-S92 -> -27.6
A99: Biofisica y ecologica | C99: 13.Variación de la demanda hídrica | D99: Multisubsectorial | E99: Porcentaje (%) | F99: Anual | G99: Nacional | H99: 2023 | I99: Instituto de Estudios Ambientales -IDEA- | M99: 2023 | O99: Cuantitativo | R99: 13.3.1. Energia 2016-2020 | S99: =S90-S93 -> 845.1
A100: Biofisica y ecologica | C100: 13.Variación de la demanda hídrica | D100: Multisubsectorial | E100: Porcentaje (%) | F100: Anual | G100: Nacional | H100: 2023 | I100: Instituto de Estudios Ambientales -IDEA- | M100: 2023 | O100: Cuantitativo | R100: 13.3.2. Mineria 2016-2020 | S100: =S91-S94 -> 413.7
...

Sheet Puntaje asignado indicador
A2: N° | B2: Nombre de la valor indicador | C2: Nombre de la descripcion del indicador | D2: Valor del indicador | E2: Tipo de dato Indicador | F2: Nombre del valor puntaje asignado | G2: Puntaje asignado para el índice de gobernanza
A3: 1 | B3: Porcentaje de los derechos ambientales en la política sectorial de derechos humanos | C3: Se asigna puntaje definitivo para el indicador sumando los resultados obtenidos en el paso 4, 5 y 8 descrito en Producto E: Documento técnico que contenga la metodología ajustada y validada para la definición y estimación de los indicadores de gobernanza ambiental del sector minero energético y el desarrollo metodológico para el cálculo de los indicadores de gobernanza para el año 2023. | D3: =IF(Variable_indicador!S6>=80,5, IF(Variable_indicador!S6>=60,3.75, IF(Variable_indicador!S6>=40,2.5, IF(Variable_indicador!S6>=20,1.25, 0))))+IF(Variable_indicador!S9>80,12, IF(Variable_indicador!S9>60,9, IF(Variable_indicador!S9>40,6, IF(Variable_indicador!S9>20,3, 0))))+IF(Variable_indicador!S10="Si", 4, 0) -> 7.75 | E3: Flotante (Float Double) | F3: Puntaje indicador reconocimiento y protección derechos ambientales | G3: =D3 -> 7.75
A4: 2 | B4: Contexto favorable para el ejercicio de los derechos ambientales | D4: =IF(Variable_indicador!S13<=20,1.4,IF(Variable_indicador!S13<=40,2.8,IF(Variable_indicador!S13<=60,4.2,IF(Variable_indicador!S13<=80,5.6,7))))+IF(Variable_indicador!S15<=20,1.4,IF(Variable_indicador!S15<=40,2.8,IF(Variable_indicador!S15<=60,4.2,IF(Variable_indicador!S15<=80,5.6,7)))) -> 2.8 | F4: Puntuación contexto favorable ejercicio de los derechos ambientales | G4: =D4 -> 2.8
A5: 3 | B5: Analisis de impacto regulatorio con dimension ambiental | D5: =IF(Variable_indicador!S18<=20,0,IF(Variable_indicador!S18<=40,5.3,IF(Variable_indicador!S18<=60,10.5,IF(Variable_indicador!S18<=80,15.3,21)))) -> 15.3 | F5: Puntuación dimensión ambiental análisis de impacto normativo | G5: =D5 -> 15.3
A6: 4 | B6: Evaluación ex post de regulaciones | D6: =IF(Variable_indicador!S19="Alta", 5, IF(Variable_indicador!S19="Baja", 0, ""))+IF(Variable_indicador!S22<=20,1,IF(Variable_indicador!S22<=40,5.3,IF(Variable_indicador!S22<=60,7,IF(Variable_indicador!S22<=80,10.5,14)))) -> 1 | F6: Valoración puntaje evaluación ex post | G6: =D6 -> 1
A7: 5 | B7: Procesos de consulta publica en la producción Normativa | D7: =IF(Variable_indicador!S25<=20,1,IF(Variable_indicador!S25<=40,5.3,IF(Variable_indicador!S25<=60,10.5,IF(Variable_indicador!S23<=80,15.3,21)))) -> 15.3 | F7: Puntaje consulta pública normatividad | G7: =D7 -> 15.3
A8: 6 | B8: Puntaje del sector de minas y energia en el indice de desempeño Institucional | D8: =IF(Variable_indicador!S29<=20,4.2,IF(Variable_indicador!S29<=40,8.4,IF(Variable_indicador!S29<=60,12.6,IF(Variable_indicador!S29<=80,18.6,21)))) -> 4.2 | F8: Puntuación promedio desempeño institucional | G8: =D8 -> 4.2
A9: 7 | B9: Coordinación interinstitucional | D9: =IF(Variable_indicador!S30="Muy alto", 4, IF(Variable_indicador!S30="Alto", 3, IF(Variable_indicador!S30="Bajo", 2, IF(Variable_indicador!S30="Muy bajo", 1, ""))))+IF(Variable_indicador!S31<=20,1,IF(Variable_indicador!S31<=40,4,IF(Variable_indicador!S31<=60,7.5,IF(Variable_indicador!S31<=80,11,15)))) -> 4 | F9: Interpretación Puntaje total para el índice | G9: =D9 -> 4
A10: 8 | B10: Acceso a la justicia | D10: =IF(Variable_indicador!S31<=20,2,IF(Variable_indicador!S31<=40,4.25,IF(Variable_indicador!S31<=60,8.5,IF(Variable_indicador!S31<=80,12.3,19)))) -> 2 | F10: Puntuación cumplimiento órdenes judiciales | G10: =D10 -> 2
A11: 9 | B11: Participación ciudadana | D11: =((Variable_indicador!S35/Variable_indicador!$S$40)*Variable_indicador!S41)*100+((Variable_indicador!S36/Variable_indicador!$S$40)*Variable_indicador!S42)*100+((Variable_indicador!S37/Variable_indicador!$S$40)*Variable_indicador!S43)*100+((Variable_indicador!S38/Variable_indicador!$S$40)*Variable_indicador!S44)*100+((Variable_indicador!S39/Variable_indicador!$S$40)*Variable_indicador!S45)*100 -> 84.899371 | E11: Flotante (Float Double) | F11: Interpretación del indicador de Participación Ciudadana | G11: =IF(D11>=90,24, IF(D11>=75,19, IF(D11>=50,15, IF(D11>=30,8, 5)))) -> 19
A12: 10 | B12: Interacción de género y enfoque diferencial | D12: =(Variable_indicador!S72+Variable_indicador!S73+Variable_indicador!S74+Variable_indicador!S75+Variable_indicador!S76+Variable_indicador!S77)/6 -> 27.625029 | E12: Flotante (Float Double) | F12: Interpretación del indicador de interacción de género y enfoque diferencial | G12: =IF(D12>40,19, IF(D12>25,15, IF(D12>10,12, IF(AND(D12>=-10,D12<=10),10, IF(AND(D12>=-25,D12<-10),8,""))))) -> 15
A13: 11 | B13: Conflictividad socioambiental | D13: =((Variable_indicador!S78+Variable_indicador!S79+Variable_indicador!S80)/Variable_indicador!S82)*100 -> 35.251799 | E13: Flotante (Float Double) | F13: Interpretación del indicador de Conflictividad socioambiental | G13: =IF(D13<=9.99,24, IF(D13<=24.99,21, IF(D13<=49.99,18, IF(D13<=74.99,12, 6)))) -> 18
A14: 12 | B14: Cumplimiento a PQRSD | D14: =(Variable_indicador!S83+Variable_indicador!S84+Variable_indicador!S85+Variable_indicador!S86)/4 -> 94.3125 | E14: Flotante (Float Double) | F14: Interpretación del indicador de Cumplimiento a PQRSD | G14: =IF(D14>=95, 22, IF(D14>=90, 16, IF(D14>75, 10, IF(D14>=70, 5, "")))) -> 16
A15: 13 | B15: Variación de la demanda hídrica | D15: =Variable_indicador!S99+Variable_indicador!S100+Variable_indicador!S101 -> 1507.5 | E15: Flotante (Float Double) | F15: Interpretación de resultados para la variación de la demanda hídrica | G15: =IF(D15>0, 17, 8) -> 17
A16: 14 | B16: Variación de la huella hidrica azul | D16: =Variable_indicador!S108+Variable_indicador!S109+Variable_indicador!S110 -> 39.6 | G16: =IF(D16>0, 17, 8) -> 17
A17: 15 | B17: Variación del área compensada para el sector minero energético | D17: =SUM(Variable_indicador!S123:S131) -> 2975.8631 | F17: Criterios para calificar la variación del área compensada en el índice de gobernanza | G17: =IF(COUNTIF(Variable_indicador!S123:S131,">0")=9,19, IF(COUNTIF(Variable_indicador!S123:S131,">0")=6,14.25, IF(COUNTIF(Variable_indicador!S123:S131,"<0")=6,9.5, IF(COUNTIF(Variable_indicador!S123:S1855,"<0")=9,4.75) ) ) ) -> 9.5
A18: 16 | B18: Área de superposición de cada subsector minero energético con determinantes ambientales | D18: =(Variable_indicador!S175+Variable_indicador!S178+Variable_indicador!S179)/3 -> 43.950026 | F18: Interpretación de resultados para la superposición del sector minero energético con determinantes ambientales | G18: =_xlfn.IFS(D18>=76,4.75,D18>=51,9.5,D18>=26,14.25,D18>=0,19) -> 14.25
A19: 17 | B19: Área de superposición de cada subsector minero energetico con areas prioritarias de conservación | D19: =(Variable_indicador!S210+Variable_indicador!S213+Variable_indicador!S216)/3 -> 34.475552 | F19: Interpretación de resultados para la superposición del sector minero energéticos con áreas de distribución de especies importantes para la conservación | G19: =_xlfn.IFS(D19>=51,5,D19>=21,10,D19<20,19) -> 10
A20: 18 | B20: Variación de la generación de residuos peligrosos (RESPEL) por unidad producida | D20: =(Variable_indicador!S244+Variable_indicador!S245+Variable_indicador!S246)/3 -> 56.339555 | F20: Interpretación resultados indicador de variación de la generación de residuos peligrosos (Respel) por unidad producida | G20: =IF(Variable_indicador!S244<=-30,7,IF(AND(Variable_indicador!S244>-30,Variable_indicador!S244<0),4,IF(AND(Variable_indicador!S244>=0,Variable_indicador!S244<30),2,IF(Variable_indicador!S244>=30,1))))+IF(Variable_indicador!S245<=-30,7,IF(AND(Variable_indicador!S245>-30,Variable_indicador!S245<0),4,IF(AND(Variable_indicador!S245>=0,Variable_indicador!S245<30),2,IF(Variable_indicador!S245>=30,1))))+ IF(Variable_indicador!S246<=-30,7,IF(AND(Variable_indicador!S246>-30,Variable_indicador!S246<0),4,IF(AND(Variable_indicador!S246>=0,Variable_indicador!S246<30),2,IF(Variable_indicador!S246>=30,1)))) -> 4
A21: 19 | B21: Licenciamiento Ambiental | D21: =((Variable_indicador!S247+Variable_indicador!S249+Variable_indicador!S251)/(Variable_indicador!S248+Variable_indicador!S250+Variable_indicador!S252))*100 -> 64.285714 | E21: Flotante (Float Double) | F21: Interpretación resultados indicador licenciamiento ambiental | G21: =IF(D21>75,19,IF(D21>50,12,IF(D21>25,7,IF(D21>=0,3,"")))) -> 12
A22: 20 | B22: Procesos sancionatorios ambientales | D22: =((Variable_indicador!S253+Variable_indicador!S254+Variable_indicador!S255)/(Variable_indicador!S256+Variable_indicador!S257+Variable_indicador!S258))*100 -> 0 | F22: Interpretación resultados indicador procesos sancionatorios ambientales | G22: =IF(D22<=25,17,IF(D22<=50,13,IF(D22<=75,8,3))) -> 17
A23: 21 | B23: Variación de emisiones de gases de efecto invernadero (GEI) del sector | D23: =Variable_indicador!S421 -> -1.0436079 | F23: Interpretación del indicador de variación de emisiones de GEI | G23: =IF(D23>10,7,IF(D23>0,12,IF(D23>=-5,17,22))) -> 17
A24: 22 | B24: Tasa de variación del financiamiento climático | D24: =((Variable_indicador!S491-Variable_indicador!S490)/Variable_indicador!S491)*100 -> -96.1969 | F24: Interpretación del indicador de variación del financiamiento climático | G24: =IF(D24<0,6,IF(D24<=20%,11,IF(D24<=30%,16,21))) -> 6
A25: 23
A26: 24 | B26: Indice de derrames de hidrocarburos (IDH) | D26: =Variable_indicador!S543/Variable_indicador!S544 -> 2.7293082 | F26: Interpretación del indicador de accidentalidad sector hidrocarburos | G26: =IF(D26<=1,24,IF(D26<=2.5,18,IF(D26>4,6,12))) -> 12
A27: 25 | B27: Índice de gravedad de accidentes mineros (IGAM) | D27: =((Variable_indicador!S592+(3*Variable_indicador!S593))/Variable_indicador!S591) -> 4.1803279 | F27: Interpretación del indicador de accidentalidad minera | G27: =IF(D27<=1,24,IF(D27<=2.5,18,IF(D27>4,6,12))) -> 6
A28: 26 | B28: índice de severidad de accidentes eléctricos (ISAE) | D28: =((Variable_indicador!S602+(3*Variable_indicador!S603))/Variable_indicador!S604) -> 1.3301887 | F28: Interpretación de indicador de accidentalidad sector energético | G28: =IF(D28<=1,24,IF(D28<=2.5,18,IF(D28>4,6,12))) -> 18
A29: 27 | B29: Variación de la intensidad energética por subsector | D29: =((Variable_indicador!S637-Variable_indicador!S638)/Variable_indicador!S637) -> -0.0012113578 | F29: Interpretación del indicador de variación de la intensidad energética por subsector. | G29: =IF(D29>3.27,14,IF(D29>1.92,10,IF(D29>=0,6,2))) -> 2
A30: 28 | B30: Variación de la intensidad energética nacional | D30: =((Variable_indicador!S655-Variable_indicador!S656)/Variable_indicador!S655) -> 0.1570209 | F30: Interpretación del indicador de variación de la intensidad energética nacional | G30: =IF(D30>3.27,14,IF(D30>1.92,10,IF(D30>=0,6,2))) -> 6
A31: 29 | B31: Participación de las fncer en la matriz energética primaria | D31: =((Variable_indicador!S680-Variable_indicador!S679)/Variable_indicador!S680)*100 -> 9.262535 | F31: Interpretación del indicador de participación de las FNCER en matriz primaria | G31: =IF(D31>15.47,17,IF(D31>0,10,5)) -> 10
A32: 30 | B32: Participación de las FNCER en la matriz energética eléctrica. | D32: =((Variable_indicador!S691/Variable_indicador!S692)-(Variable_indicador!S685/Variable_indicador!S686))/(Variable_indicador!S691/Variable_indicador!S692)*100 -> 36.4448 | E32: Flotante (Float Double) | G32: =IF(D32>=50,17,IF(D32>=35,11,IF(D32>=15,6,1))) -> 11
A33: 31 | B33: Producción de minerales estratégicos y críticos para la TEJ. | D33: =Variable_indicador!S694-Variable_indicador!S693 -> 7302438.8 | F33: Interpretación del indicador de producción de minerales estratégicos y críticos para la TEJ. | G33: =IF(D33>=8000000,17,IF(D33>4000000,10, 0)) -> 10
A34: 32 | B34: Pobreza multidimensional en municipios productores de minerales estratégicos | D34: =((Variable_indicador!S700-Variable_indicador!S699)/Variable_indicador!S700)*100 -> 8.3333333 | F34: Interpretación del indicador de pobreza multidimensional en municipios productores de minerales estratégicos para la TEJ | G34: =IF(D34>20,17,IF(D34>=1,13,IF(D34=0,9,IF(D34>=-20,5,1)))) -> 13
A35: 33 | B35: Recaudo efectivo de regalías | D35: =(Variable_indicador!S701/Variable_indicador!S702)*100 -> 117.03663 | F35: Interpretación del indicador de recaudo efectivo de regalías | G35: =IF(D35>100,21,8) -> 21
A36: 34 | B36: Regalías destinadas al sector ambiente y desarrollo sostenible | D36: =(Variable_indicador!S703/Variable_indicador!S704)*100 -> 98.519794 | F36: Interpretación del indicador de regalías destinadas al sector ambiente y de desarrollo sostenible | G36: =IF(D36>=96,19,IF(D36>=91,16,IF(D36>=86,10,5))) -> 19
A37: 35 | B37: Variación de proyectos del SGR dirigidos al sector ambiente y desarrollo sostenible | D37: =((Variable_indicador!S705-Variable_indicador!S706)/Variable_indicador!S706)*100 -> 186.09272 | F37: Interpretación del indicador de variación de proyectos del SGR dirigidos al sector ambiente y desarrollo sostenible | G37: =IF(D37>150,14,IF(D37>=100,12,IF(D37>=70,7,5))) -> 14
A38: 36 | B38: Participación del sector minero energético en el PIB nacional | D38: =(Variable_indicador!S707/Variable_indicador!S708)*100 -> 6.2583221 | F38: Interpretación del indicador de participación del sector minero energético en el PIB nacional | G38: =IF(D38<=8.33,17,IF(D38<=13.81,12,IF(D38<=19.29,8,4))) -> 17
A39: 37 | B39: Participación del sector minero energético en las exportaciones del país | D39: =((Variable_indicador!S709/Variable_indicador!S710)*100) -> 52.52135 | F39: Interpretación del indicador de participación del sector minero energético en las exportaciones del país | G39: =IF(D39<=25,11,IF(D39<=44,7,IF(D39<=63,3.5,1))) -> 3.5
A40: 38 | B40: Pobreza multidimensional en municipios productores de hidrocarburos. | D40: =((Variable_indicador!S716-Variable_indicador!S713)/Variable_indicador!S716)*100 -> 6.3941406 | F40: Interpretación del Indicador de Diferencia Relativa Promedio IPM | G40: =IF(D40>20,14,IF(D40>=11,12,IF(D40>=1,10,IF(D40=0,8,IF(D40>=-10,6,IF(D40>=-20,4,2)))))) -> 10
A41: 39 | B41: Índice de cobertura y equidad territorial en municipios productores | D41: =((Variable_indicador!S717/Variable_indicador!S719)*(Variable_indicador!S718/Variable_indicador!S720))*100 -> 2.8199654 | F41: Interpretación del resultado del indicador de cobertura y equidad territorial en municipios productores | G41: =IF(D41>=15,24,IF(D41>=10,18,IF(D41>=5,12,6))) -> 6
A42: 40 | B42: Participación de los hidrocarburos en la matriz energética (IPHME) | D42: =(Variable_indicador!S721/Variable_indicador!S722)*100 -> 62.891867 | F42: Interpretación del resultado del indicador participación de los hidrocarburos en la matriz energética | G42: =IF(D42>60,7,IF(D42>=40,14,21)) -> 7
A43: 41 | B43: Variación del stock de hidrocarburos | D43: =((Variable_indicador!S728-Variable_indicador!S725)/Variable_indicador!S725)*100 -> -5.1747093 | F43: Interpretación del resultado indicador variación del stock de hidrocarburos | G43: =IF(D43>0,21,IF(D43=0,14,7)) -> 7
A44: 42 | B44: Disponibilidad de reservas de hidrocarburos (R/P) | D44: =Variable_indicador!S734/Variable_indicador!S731 -> 6.8212154 | F44: Interpretación del resultado indicador disponibilidad de reservas de hidrocarburos R/P | G44: =IF(D44>50,21,IF(D44>=30,16,IF(D44>=15,11,6))) -> 6
A45: 43 | B45: Tasa de extracción de hidrocarburos (TEH) | D45: =(Variable_indicador!S737/(Variable_indicador!S740+Variable_indicador!S741))*100 -> 12.762135 | F45: Interpretación del resultado indicador tasa de extracción de hidrocarburos | G45: =IF(D45<2,21,IF(D45<=5,16,IF(D45<=10,11,6))) -> 6
A46: 44 | B46: Superposición de títulos mineros activos con áreas ambientales excluibles, restrictivas e informativas para la minería | D46: =G46 -> 7 | F46: Resultados e Interpretación del porcentaje de superposición de áreas con la ponderación del índice de gobernanza año 2023 | G46: =IF(Variable_indicador!S821="Alta",1,IF(Variable_indicador!S821="Moderada",4,IF(Variable_indicador!S821="Baja",7,IF(Variable_indicador!S821="Nula",10,""))))+IF(Variable_indicador!S822="Alta",1,IF(Variable_indicador!S822="Moderada",3,IF(Variable_indicador!S822="Baja",6,IF(Variable_indicador!S822="Nula",8,""))))+IF(Variable_indicador!S823="Alta",1,IF(Variable_indicador!S823="Moderada",2,IF(Variable_indicador!S823="Baja",4,IF(Variable_indicador!S823="Nula",6,"")))) -> 7
A47: 45 | B47: Superposición de áreas de reserva especial declaradas y solicitadas con áreas ambientales excluibles, restrictivas e informativas para la minería | D47: =G47 -> 7 | F47: Resultados e Interpretación del porcentaje de superposición de áreas con la ponderación del índice de gobernanza año 2024 | G47: =IF(Variable_indicador!S846="Alta",1,IF(Variable_indicador!S846="Moderada",4,IF(Variable_indicador!S846="Baja",7,IF(Variable_indicador!S846="Nula",10,""))))+IF(Variable_indicador!S847="Alta",1,IF(Variable_indicador!S847="Moderada",3,IF(Variable_indicador!S847="Baja",6,IF(Variable_indicador!S847="Nula",8,""))))+IF(Variable_indicador!S848="Alta",1,IF(Variable_indicador!S848="Moderada",2,IF(Variable_indicador!S848="Baja",4,IF(Variable_indicador!S848="Nula",6,"")))) -> 7
A48: 46 | B48: Procesos de formalización y registro minero | D48: =(Variable_indicador!S876+Variable_indicador!S877+Variable_indicador!S878+Variable_indicador!S879)/4 -> 21.48638 | F48: Interpretación eficiencia consecución de procesos de formalización minera y puntaje de ponderación del índice de gobernanza | G48: =IF(D48<30,5,IF(D48<70,2,21)) -> 5
A49: 47 | B49: Áreas recuperadas por gestión y control a la explotación ilegal de minerales | D49: =G49 -> 5 | F49: Ponderación resultados año 2022 | G49: =IF(Variable_indicador!S886>=0,5,2)+IF(Variable_indicador!S887>=0,4,1)+IF(Variable_indicador!S888>=0,2,5) -> 5
A50: 48 | B50: Variación del Consumo de Energía Eléctrica en el país. | D50: =((Variable_indicador!S891-Variable_indicador!S894)/Variable_indicador!S891)*100 -> 13.942122 | F50: Categorización del indicador. | G50: =IF(D50>0,24,IF(D50<0,2,"")) -> 24
A51: 49 | B51: Variación en el nivel de pobreza energética multidimensional nacional. | D51: =((Variable_indicador!S896-Variable_indicador!S895)/Variable_indicador!S896)*100 -> 3.5991966 | F51: Categorización del indicador. | G51: =IF(D51>3,22,IF(D51>=1,18,IF(D51>=0,12,2))) -> 22
A52: 50 | B52: Variación en la cobertura en el acceso al servicio de energía eléctrica en el país. | D52: =Variable_indicador!S900-Variable_indicador!S899 -> 0.40307073 | F52: Categorización Indicador. | G52: =IF(D52>0,24,IF(D52<0,2,"")) -> 24
A53: 51 | B53: Porcentaje de Informes de Sostenibilidad anuales publicados por empresas generadoras del país. | D53: =(Variable_indicador!S901/Variable_indicador!S902)*100 -> 54.545455 | F53: Categorización Indicador. | G53: =IF(D53>80,21,IF(D53>=40,14,7)) -> 14

Sheet Ponderado indicador
A1: N° | B1: Dimensión | C1: Objetivos | D1: Atributo | E1: Índice / Indicador | F1: Ficha Metodologica | G1: Criterio 1 ¿El indicador tiene un relación directa y significativa con la definición de gobernanza? Si/No | H1: Criterio 2 ¿El indicador puede ser mejorado a través de la gestión del Ministerio de Minas y Energía? Si/No | I1: Criterio 3 ¿El indicador tiene relación con el cumplimiento normativo del sector minero o ambiental ? Si/No | J1: Criterio 4¿La información requerida para la medición del indicador es generada por el Ministerio de Minas y Energía y/o sus entidades adscritas o vinculadas? Si/NO | K1: Criterio 5 ¿El indicador tiene una frecuencia de medición igual o inferior a un año? Si/No | L1: Criterio 6¿A partir de los resultados del indicador, el Ministerio de Minas y Energía puede emprender acciones que se concreten en la reglamentación del sector o en la definición de políticas, planes, programas o proyectos? Si/No | M1: Criterio 1 | N1: Criterio 2 | O1: Criterio 3 | P1: Criterio 4 | Q1: Criterio 5 | R1: Criterio 6 | S1: Criterio 7 Calificación promedio de la dimensión al que corresponde el indicador, en los talleres regionales | T1: Criterio 8 Calificación promedio del indicador en los talleres regionales | U1: Total | V1: Normalización | W1: Aproximación a la unidad
A2: 1 | B2: Análisis jurídico-normativo | C2: Robustez | D2: Legitimidad | E2: Reconocimiento y protección de los derechos ambientales en la política sectorial de derechos humanos | F2: 01. Reconocimiento y protección de los derechos ambientales.docx | G2: Si | H2: Si | I2: Si | J2: No | K2: Si | L2: Si | M2: =IF(G2="SI", 5, 1) -> 5 | N2: =IF(H2="SI", 5, 1) -> 5 | O2: =IF(I2="SI", 5, 1) -> 5 | P2: =IF(J2="SI", 5, 1) -> 1 | Q2: =IF(K2="SI", 5, 1) -> 5 | R2: =IF(L2="SI", 5, 1) -> 5 | S2: 4.3333333 | T2: 4.5142857 | U2: =SUM(M2:T2) -> 34.847619 | V2: =(Tabla1[[#This Row],[Total]]/$U$53)*1000 -> 21.467757 | W2: =ROUND(Tabla1[[#This Row],[Normalización]],0) -> 21
A3: 2 | B3: Análisis jurídico-normativo | C3: Robustez | D3: Legitimidad | E3: Contexto favorable para el ejercicio de los derechos ambientales | F3: 02. Contexto favorable para el ejercicio de los derechos ambientales.docx | G3: Si | H3: No | I3: No | J3: No | K3: Si | L3: No | M3: =IF(G3="SI", 5, 1) -> 5 | N3: =IF(H3="SI", 5, 1) -> 1 | O3: =IF(I3="SI", 5, 1) -> 1 | P3: =IF(J3="SI", 5, 1) -> 1 | Q3: =IF(K3="SI", 5, 1) -> 5 | R3: =IF(L3="SI", 5, 1) -> 1 | S3: 4.3333333 | T3: 4.3529412 | U3: =SUM(M3:T3) -> 22.686275 | V3: =(Tabla1[[#This Row],[Total]]/$U$53)*1000 -> 13.975802 | W3: =ROUND(Tabla1[[#This Row],[Normalización]],0) -> 14
A4: 3 | B4: Análisis jurídico-normativo | C4: Equidad | D4: Reconocimiento, Participación, Transparencia | E4: Análisis de impacto regulatorio con dimensión ambiental | F4: 03. Análisis de impacto regulatorio con dimensión ambiental.docx | G4: Si | H4: Si | I4: Si | J4: Si | K4: Si | L4: No | M4: =IF(G4="SI", 5, 1) -> 5 | N4: =IF(H4="SI", 5, 1) -> 5 | O4: =IF(I4="SI", 5, 1) -> 5 | P4: =IF(J4="SI", 5, 1) -> 5 | Q4: =IF(K4="SI", 5, 1) -> 5 | R4: =IF(L4="SI", 5, 1) -> 1 | S4: 4.3333333 | T4: 4.03125 | U4: =SUM(M4:T4) -> 34.364583 | V4: =(Tabla1[[#This Row],[Total]]/$U$53)*1000 -> 21.170185 | W4: =ROUND(Tabla1[[#This Row],[Normalización]],0) -> 21
A5: 4 | B5: Análisis jurídico-normativo | C5: Equidad | D5: Reconocimiento, Participación, Transparencia | E5: Evaluación ex post de regulaciones | F5: 04. Evaluación ex post de regulaciones.docx | G5: No | H5: Si | I5: Si | J5: Si | K5: Si | L5: No | M5: =IF(G5="SI", 5, 1) -> 1 | N5: =IF(H5="SI", 5, 1) -> 5 | O5: =IF(I5="SI", 5, 1) -> 5 | P5: =IF(J5="SI", 5, 1) -> 5 | Q5: =IF(K5="SI", 5, 1) -> 5 | R5: =IF(L5="SI", 5, 1) -> 1 | S5: 4.3333333 | T5: 4.1515152 | U5: =SUM(M5:T5) -> 30.484848 | V5: =(Tabla1[[#This Row],[Total]]/$U$53)*1000 -> 18.780087 | W5: =ROUND(Tabla1[[#This Row],[Normalización]],0) -> 19
A6: 5 | B6: Análisis jurídico-normativo | C6: Equidad | D6: Reconocimiento, Participación, Transparencia | E6: Procesos de consulta pública en la producción normativa | F6: 05. Procesos de consulta pública en la producción normativa.docx | G6: Si | H6: Si | I6: Si | J6: Si | K6: Si | L6: No | M6: =IF(G6="SI", 5, 1) -> 5 | N6: =IF(H6="SI", 5, 1) -> 5 | O6: =IF(I6="SI", 5, 1) -> 5 | P6: =IF(J6="SI", 5, 1) -> 5 | Q6: =IF(K6="SI", 5, 1) -> 5 | R6: =IF(L6="SI", 5, 1) -> 1 | S6: 4.3333333 | T6: 4.3636364 | U6: =SUM(M6:T6) -> 34.69697 | V6: =(Tabla1[[#This Row],[Total]]/$U$53)*1000 -> 21.37495 | W6: =ROUND(Tabla1[[#This Row],[Normalización]],0) -> 21
A7: 6 | B7: Análisis institucional | C7: Efectividad | D7: Coordinación, dirección, capacidad y eficiencia | E7: Puntaje del sector de minas y energía en el índice de Desempeño Institucional | F7: 06. Puntaje del SME en el Índice de Desempaño Institucional.docx | G7: Si | H7: Si | I7: Si | J7: No | K7: Si | L7: Si | M7: =IF(G7="SI", 5, 1) -> 5 | N7: =IF(H7="SI", 5, 1) -> 5 | O7: =IF(I7="SI", 5, 1) -> 5 | P7: =IF(J7="SI", 5, 1) -> 1 | Q7: =IF(K7="SI", 5, 1) -> 5 | R7: =IF(L7="SI", 5, 1) -> 5 | S7: 4.4333333 | T7: 4.2941176 | U7: =SUM(M7:T7) -> 34.727451 | V7: =(Tabla1[[#This Row],[Total]]/$U$53)*1000 -> 21.393728 | W7: =ROUND(Tabla1[[#This Row],[Normalización]],0) -> 21
A8: 7 | B8: Análisis institucional | C8: Efectividad | D8: Coordinación, dirección, capacidad y eficiencia | E8: Coordinación intersectorial | F8: 07. Coordinación interinstitucional.docx | G8: Si | H8: No | I8: Si | J8: No | K8: Si | L8: Si | M8: =IF(G8="SI", 5, 1) -> 5 | N8: =IF(H8="SI", 5, 1) -> 1 | O8: =IF(I8="SI", 5, 1) -> 5 | P8: =IF(J8="SI", 5, 1) -> 1 | Q8: =IF(K8="SI", 5, 1) -> 5 | R8: =IF(L8="SI", 5, 1) -> 5 | S8: 4.4333333 | T8: 4.4705882 | U8: =SUM(M8:T8) -> 30.903922 | V8: =(Tabla1[[#This Row],[Total]]/$U$53)*1000 -> 19.038256 | W8: =ROUND(Tabla1[[#This Row],[Normalización]],0) -> 19
A9: 8 | B9: Análisis institucional | C9: Equidad | D9: Reconocimiento y justicia | E9: Acceso a justicia | F9: 08. Acceso a justicia.docx | G9: Si | H9: No | I9: Si | J9: No | K9: Si | L9: Si | M9: =IF(G9="SI", 5, 1) -> 5 | N9: =IF(H9="SI", 5, 1) -> 1 | O9: =IF(I9="SI", 5, 1) -> 5 | P9: =IF(J9="SI", 5, 1) -> 1 | Q9: =IF(K9="SI", 5, 1) -> 5 | R9: =IF(L9="SI", 5, 1) -> 5 | S9: 4.4333333 | T9: 4.6285714 | U9: =SUM(M9:T9) -> 31.061905 | V9: =(Tabla1[[#This Row],[Total]]/$U$53)*1000 -> 19.135581 | W9: =ROUND(Tabla1[[#This Row],[Normalización]],0) -> 19
A10: 9 | B10: Social | C10: Equidad | D10: Participación | E10: Participación ciudadana | F10: 09. Participación Ciudadana.docx | G10: Si | H10: Si | I10: Si | J10: Si | K10: Si | L10: Si | M10: =IF(G10="SI", 5, 1) -> 5 | N10: =IF(H10="SI", 5, 1) -> 5 | O10: =IF(I10="SI", 5, 1) -> 5 | P10: =IF(J10="SI", 5, 1) -> 5 | Q10: =IF(K10="SI", 5, 1) -> 5 | R10: =IF(L10="SI", 5, 1) -> 5 | S10: 4.62 | T10: 4.68 | U10: =SUM(M10:T10) -> 39.3 | V10: =(Tabla1[[#This Row],[Total]]/$U$53)*1000 -> 24.210631 | W10: =ROUND(Tabla1[[#This Row],[Normalización]],0) -> 24
A11: 10 | B11: Social | C11: Equidad | D11: Reconocimiento | E11: Interacción de género y enfoque diferencial | F11: 10. Interacción de género y enfoque diferencial.docx | G11: Si | H11: Si | I11: No | J11: Si | K11: Si | L11: No | M11: =IF(G11="SI", 5, 1) -> 5 | N11: =IF(H11="SI", 5, 1) -> 5 | O11: =IF(I11="SI", 5, 1) -> 1 | P11: =IF(J11="SI", 5, 1) -> 5 | Q11: =IF(K11="SI", 5, 1) -> 5 | R11: =IF(L11="SI", 5, 1) -> 1 | S11: 4.62 | T11: 4.49 | U11: =SUM(M11:T11) -> 31.11 | V11: =(Tabla1[[#This Row],[Total]]/$U$53)*1000 -> 19.16521 | W11: =ROUND(Tabla1[[#This Row],[Normalización]],0) -> 19
A12: 11 | B12: Social | C12: Equidad | D12: Justicia | E12: Conflictividad socioambiental | F12: 11. Conflictividad Socioambiental.docx | G12: Si | H12: Si | I12: Si | J12: Si | K12: Si | L12: Si | M12: =IF(G12="SI", 5, 1) -> 5 | N12: =IF(H12="SI", 5, 1) -> 5 | O12: =IF(I12="SI", 5, 1) -> 5 | P12: =IF(J12="SI", 5, 1) -> 5 | Q12: =IF(K12="SI", 5, 1) -> 5 | R12: =IF(L12="SI", 5, 1) -> 5 | S12: 4.62 | T12: 4.69 | U12: =SUM(M12:T12) -> 39.31 | V12: =(Tabla1[[#This Row],[Total]]/$U$53)*1000 -> 24.216792 | W12: =ROUND(Tabla1[[#This Row],[Normalización]],0) -> 24
A13: 12 | B13: Social | C13: Equidad | D13: Transparencia | E13: Cumplimiento a PQRSD | F13: 12. Cumplimiento a PQRSD (peticiones, quejas, reclamos, sugerencias y denuncias).docx | G13: Si | H13: Si | I13: Si | J13: Si | K13: Si | L13: No | M13: =IF(G13="SI", 5, 1) -> 5 | N13: =IF(H13="SI", 5, 1) -> 5 | O13: =IF(I13="SI", 5, 1) -> 5 | P13: =IF(J13="SI", 5, 1) -> 5 | Q13: =IF(K13="SI", 5, 1) -> 5 | R13: =IF(L13="SI", 5, 1) -> 1 | S13: 4.62 | T13: 4.49 | U13: =SUM(M13:T13) -> 35.11 | V13: =(Tabla1[[#This Row],[Total]]/$U$53)*1000 -> 21.629396 | W13: =ROUND(Tabla1[[#This Row],[Normalización]],0) -> 22
... A32: 31 | B32: Transición energética justa | C32: Receptividad | D32: Flexibilidad y Adaptación | E32: Producción de minerales estratégicos y críticos para la TEJ. | F32: 31. Producción de Minerales Estratégicos y Críticos para la TEJ.docx | G32: Si | H32: No | I32: No | J32: Si | K32: Si | L32: No | M32: =IF(G32="SI", 5, 1) -> 5 | N32: =IF(H32="SI", 5, 1) -> 1 | O32: =IF(I32="SI", 5, 1) -> 1 | P32: =IF(J32="SI", 5, 1) -> 5 | Q32: =IF(K32="SI", 5, 1) -> 5 | R32: =IF(L32="SI", 5, 1) -> 1 | S32: 4.52 | T32: 4.28 | U32: =SUM(M32:T32) -> 26.8 | V32: =(Tabla1[[#This Row],[Total]]/$U$53)*1000 -> 16.510049 | W32: =ROUND(Tabla1[[#This Row],[Normalización]],0) -> 17
A33: 32 | B33: Transición energética justa | D33: Equidad | E33: Pobreza multidimensional en municipios productores de minerales estratégicos | F33: 32. Pobreza multidimensional en municipios productores de minerales estratégicos para la Transición Energética Justa..docx | G33: Si | H33: No | I33: No | J33: No | K33: Si | L33: Si | M33: =IF(G33="SI", 5, 1) -> 5 | N33: =IF(H33="SI", 5, 1) -> 1 | O33: =IF(I33="SI", 5, 1) -> 1 | P33: =IF(J33="SI", 5, 1) -> 1 | Q33: =IF(K33="SI", 5, 1) -> 5 | R33: =IF(L33="SI", 5, 1) -> 5 | S33: 4.52 | T33: 4.52 | U33: =SUM(M33:T33) -> 27.04 | V33: =(Tabla1[[#This Row],[Total]]/$U$53)*1000 -> 16.6579 | W33: =ROUND(Tabla1[[#This Row],[Normalización]],0) -> 17
A34: 33 | B34: Económica | C34: Efectividad | D34: Eficiencia | E34: Recaudo efectivo de regalías | F34: 33. Recaudo efectivo de Regalías.docx | G34: Si | H34: Si | I34: Si | J34: No | K34: Si | L34: Si | M34: =IF(G34="SI", 5, 1) -> 5 | N34: =IF(H34="SI", 5, 1) -> 5 | O34: =IF(I34="SI", 5, 1) -> 5 | P34: =IF(J34="SI", 5, 1) -> 1 | Q34: =IF(K34="SI", 5, 1) -> 5 | R34: =IF(L34="SI", 5, 1) -> 5 | S34: 4.22 | T34: 4.345 | U34: =SUM(M34:T34) -> 34.565 | V34: =(Tabla1[[#This Row],[Total]]/$U$53)*1000 -> 21.293651 | W34: =ROUND(Tabla1[[#This Row],[Normalización]],0) -> 21
A35: 34 | B35: Económica | C35: Efectividad | D35: Eficiencia | E35: Regalías destinadas al sector ambiente y desarrollo sostenible | F35: 34. Regalías destinadas al sector Ambiente y Desarrollo Sostenible.docx | G35: No | H35: Si | I35: Si | J35: No | K35: Si | L35: Si | M35: =IF(G35="SI", 5, 1) -> 1 | N35: =IF(H35="SI", 5, 1) -> 5 | O35: =IF(I35="SI", 5, 1) -> 5 | P35: =IF(J35="SI", 5, 1) -> 1 | Q35: =IF(K35="SI", 5, 1) -> 5 | R35: =IF(L35="SI", 5, 1) -> 5 | S35: 4.22 | T35: 4.655 | U35: =SUM(M35:T35) -> 30.875 | V35: =(Tabla1[[#This Row],[Total]]/$U$53)*1000 -> 19.020439 | W35: =ROUND(Tabla1[[#This Row],[Normalización]],0) -> 19
A36: 35 | B36: Económica | C36: Efectividad | D36: Eficiencia | E36: Variación de proyectos del SGR dirigidos al sector ambiente y desarrollo sostenible | F36: 35. Variación del número de proyectos del SGR dirigidos al sector Ambiente y Desarrollo Sostenible.docx | G36: No | H36: No | I36: No | J36: No | K36: Si | L36: Si | M36: =IF(G36="SI", 5, 1) -> 1 | N36: =IF(H36="SI", 5, 1) -> 1 | O36: =IF(I36="SI", 5, 1) -> 1 | P36: =IF(J36="SI", 5, 1) -> 1 | Q36: =IF(K36="SI", 5, 1) -> 5 | R36: =IF(L36="SI", 5, 1) -> 5 | S36: 4.22 | T36: 4.28 | U36: =SUM(M36:T36) -> 22.5 | V36: =(Tabla1[[#This Row],[Total]]/$U$53)*1000 -> 13.861048 | W36: =ROUND(Tabla1[[#This Row],[Normalización]],0) -> 14
A37: 36 | B37: Económica | C37: Efectividad | D37: Eficiencia | E37: Participación del sector minero energético en el PIB nacional | F37: 36. Participación del sector Minero Energético en el PIB nacional.docx | G37: Si | H37: No | I37: Si | J37: No | K37: Si | L37: No | M37: =IF(G37="SI", 5, 1) -> 5 | N37: =IF(H37="SI", 5, 1) -> 1 | O37: =IF(I37="SI", 5, 1) -> 5 | P37: =IF(J37="SI", 5, 1) -> 1 | Q37: =IF(K37="SI", 5, 1) -> 5 | R37: =IF(L37="SI", 5, 1) -> 1 | S37: 4.22 | T37: 4.69 | U37: =SUM(M37:T37) -> 26.91 | V37: =(Tabla1[[#This Row],[Total]]/$U$53)*1000 -> 16.577814 | W37: =ROUND(Tabla1[[#This Row],[Normalización]],0) -> 17
A38: 37 | B38: Económica | C38: Efectividad | D38: Eficiencia | E38: Participación del sector minero energético en las exportaciones del país | F38: 37. Participación del sector Minero Energético en las exportaciones del país.docx | G38: No | H38: No | I38: No | J38: No | K38: Si | L38: No | M38: =IF(G38="SI", 5, 1) -> 1 | N38: =IF(H38="SI", 5, 1) -> 1 | O38: =IF(I38="SI", 5, 1) -> 1 | P38: =IF(J38="SI", 5, 1) -> 1 | Q38: =IF(K38="SI", 5, 1) -> 5 | R38: =IF(L38="SI", 5, 1) -> 1 | S38: 4.22 | T38: 4.31 | U38: =SUM(M38:T38) -> 18.53 | V38: =(Tabla1[[#This Row],[Total]]/$U$53)*1000 -> 11.415343 | W38: =ROUND(Tabla1[[#This Row],[Normalización]],0) -> 11
A39: 38 | B39: Subsector de hidrocarburos | C39: Equidad | D39: Justicia | E39: Pobreza multidimensional en municipios productores de hidrocarburos. | F39: 38. Pobreza multidimensional en municipios productores de hidrocarburos..docx | G39: Si | H39: Si | I39: No | J39: No | K39: No | L39: No | M39: =IF(G39="SI", 5, 1) -> 5 | N39: =IF(H39="SI", 5, 1) -> 5 | O39: =IF(I39="SI", 5, 1) -> 1 | P39: =IF(J39="SI", 5, 1) -> 1 | Q39: =IF(K39="SI", 5, 1) -> 1 | R39: =IF(L39="SI", 5, 1) -> 1 | S39: 4.23 | T39: 4.61 | U39: =SUM(M39:T39) -> 22.84 | V39: =(Tabla1[[#This Row],[Total]]/$U$53)*1000 -> 14.070504 | W39: =ROUND(Tabla1[[#This Row],[Normalización]],0) -> 14
A40: 39 | B40: Subsector de hidrocarburos | C40: Equidad | D40: Justicia | E40: Índice de cobertura y equidad territorial en municipios productores | F40: 39. Cobertura y equidad territorial en municipios productores de hidrocarburos.docx | G40: Si | H40: Si | I40: Si | J40: Si | K40: Si | L40: Si | M40: =IF(G40="SI", 5, 1) -> 5 | N40: =IF(H40="SI", 5, 1) -> 5 | O40: =IF(I40="SI", 5, 1) -> 5 | P40: =IF(J40="SI", 5, 1) -> 5 | Q40: =IF(K40="SI", 5, 1) -> 5 | R40: =IF(L40="SI", 5, 1) -> 5 | S40: 4.23 | T40: 4.43 | U40: =SUM(M40:T40) -> 38.66 | V40: =(Tabla1[[#This Row],[Total]]/$U$53)*1000 -> 23.816362 | W40: =ROUND(Tabla1[[#This Row],[Normalización]],0) -> 24
A41: 40 | B41: Subsector de hidrocarburos | C41: Receptividad | D41: Anticipación | E41: Participación de los hidrocarburos en la matriz energética (IPHME) | F41: 40. Participación de los hidrocarburos en la matriz energética (IPHME).docx | G41: Si | H41: Si | I41: No | J41: Si | K41: Si | L41: Si | M41: =IF(G41="SI", 5, 1) -> 5 | N41: =IF(H41="SI", 5, 1) -> 5 | O41: =IF(I41="SI", 5, 1) -> 1 | P41: =IF(J41="SI", 5, 1) -> 5 | Q41: =IF(K41="SI", 5, 1) -> 5 | R41: =IF(L41="SI", 5, 1) -> 5 | S41: 4.23 | T41: 4.23 | U41: =SUM(M41:T41) -> 34.46 | V41: =(Tabla1[[#This Row],[Total]]/$U$53)*1000 -> 21.228966 | W41: =ROUND(Tabla1[[#This Row],[Normalización]],0) -> 21
A42: 41 | B42: Subsector de hidrocarburos | C42: Efectividad | D42: Información | E42: Variación del stock de hidrocarburos | F42: 41. Variación del stock de hidrocarburos.docx | G42: Si | H42: Si | I42: No | J42: Si | K42: Si | L42: Si | M42: =IF(G42="SI", 5, 1) -> 5 | N42: =IF(H42="SI", 5, 1) -> 5 | O42: =IF(I42="SI", 5, 1) -> 1 | P42: =IF(J42="SI", 5, 1) -> 5 | Q42: =IF(K42="SI", 5, 1) -> 5 | R42: =IF(L42="SI", 5, 1) -> 5 | S42: 4.23 | T42: 4.25 | U42: =SUM(M42:T42) -> 34.48 | V42: =(Tabla1[[#This Row],[Total]]/$U$53)*1000 -> 21.241287 | W42: =ROUND(Tabla1[[#This Row],[Normalización]],0) -> 21
A43: 42 | B43: Subsector de hidrocarburos | C43: Efectividad | D43: Información | E43: Disponibilidad de reservas de hidrocarburos (R/P) | F43: 42. Disponibilidad de reservas de hidrocarburos.docx | G43: Si | H43: Si | I43: No | J43: Si | K43: Si | L43: Si | M43: =IF(G43="SI", 5, 1) -> 5 | N43: =IF(H43="SI", 5, 1) -> 5 | O43: =IF(I43="SI", 5, 1) -> 1 | P43: =IF(J43="SI", 5, 1) -> 5 | Q43: =IF(K43="SI", 5, 1) -> 5 | R43: =IF(L43="SI", 5, 1) -> 5 | S43: 4.23 | T43: 4.32 | U43: =SUM(M43:T43) -> 34.55 | V43: =(Tabla1[[#This Row],[Total]]/$U$53)*1000 -> 21.28441 | W43: =ROUND(Tabla1[[#This Row],[Normalización]],0) -> 21
A44: 43 | B44: Subsector de hidrocarburos | C44: Efectividad | D44: Información | E44: Tasa de extracción de hidrocarburos (TEH) | F44: 43. Tasa de extracción de hidrocarburos (TEH).docx | G44: Si | H44: Si | I44: No | J44: Si | K44: Si | L44: Si | M44: =IF(G44="SI", 5, 1) -> 5 | N44: =IF(H44="SI", 5, 1) -> 5 | O44: =IF(I44="SI", 5, 1) -> 1 | P44: =IF(J44="SI", 5, 1) -> 5 | Q44: =IF(K44="SI", 5, 1) -> 5 | R44: =IF(L44="SI", 5, 1) -> 5 | S44: 4.23 | T44: 4.25 | U44: =SUM(M44:T44) -> 34.48 | V44: =(Tabla1[[#This Row],[Total]]/$U$53)*1000 -> 21.241287 | W44: =ROUND(Tabla1[[#This Row],[Normalización]],0) -> 21
A45: 44 | B45: Subsector de minería | C45: Robustez | D45: Legitimidad - Cumplimiento legal | E45: Superposición de títulos mineros activos con áreas ambientales excluibles, restrictivas e informativas para la minería | F45: 44. Superposición de títulos mineros activos con áreas ambientales excluibles....docx | G45: Si | H45: Si | I45: Si | J45: Si | K45: Si | L45: Si | M45: =IF(G45="SI", 5, 1) -> 5 | N45: =IF(H45="SI", 5, 1) -> 5 | O45: =IF(I45="SI", 5, 1) -> 5 | P45: =IF(J45="SI", 5, 1) -> 5 | Q45: =IF(K45="SI", 5, 1) -> 5 | R45: =IF(L45="SI", 5, 1) -> 5 | S45: 4.12 | T45: 4.34 | U45: =SUM(M45:T45) -> 38.46 | V45: =(Tabla1[[#This Row],[Total]]/$U$53)*1000 -> 23.693152 | W45: =ROUND(Tabla1[[#This Row],[Normalización]],0) -> 24
... A52: 51 | B52: Subsector de energía eléctrica | C52: Equidad | D52: Participación – Acceso a la Información | E52: Porcentaje de Informes de Sostenibilidad anuales publicados por empresas generadoras del país. | F52: 51. Porcentaje de Informes de Sostenibilidad anuales publicados por empresas generadoras del país..docx | G52: Si | H52: Si | I52: Si | J52: No | K52: Si | L52: Si | M52: =IF(G52="SI", 5, 1) -> 5 | N52: =IF(H52="SI", 5, 1) -> 5 | O52: =IF(I52="SI", 5, 1) -> 5 | P52: =IF(J52="SI", 5, 1) -> 1 | Q52: =IF(K52="SI", 5, 1) -> 5 | R52: =IF(L52="SI", 5, 1) -> 5 | S52: 4.3703704 | T52: 4.1724138 | U52: =SUM(M52:T52) -> 34.542784 | V52: =(Tabla1[[#This Row],[Total]]/$U$53)*1000 -> 21.279965 | W52: =ROUND(Tabla1[[#This Row],[Normalización]],0) -> 21
U53: =SUM(U2:U52) -> 1623.2538 | V53: =SUM(V2:V52) -> 1000 | W53: =SUBTOTAL(109,Tabla1[Aproximación a la unidad]) -> 1000

Sheet Tb
A3: Etiquetas de fila | B3: Suma de Puntaje para la gobernanza | C3: Suma de Puntaje máximo del indicador | E3: Dimension | F3: Porcentaje | G3: Porcentaje restante | I3: Indicadores
A4: Análisis institucional | B4: 27 | C4: 59 | E4: =A4 -> Análisis institucional | F4: =GETPIVOTDATA("Suma de Puntaje para la gobernanza",$A$3,"Dimensión","Análisis institucional")/GETPIVOTDATA("Suma de Puntaje máximo del indicador",$A$3,"Dimensión","Análisis institucional") -> 0.45762712 | G4: =200%-F4 -> 1.5423729 | I4: Base
A5: Análisis jurídico-normativo | B5: 42.4 | C5: 96 | E5: =A5 -> Análisis jurídico-normativo | F5: =GETPIVOTDATA("Suma de Puntaje para la gobernanza",$A$3,"Dimensión","Análisis jurídico-normativo")/GETPIVOTDATA("Suma de Puntaje máximo del indicador",$A$3,"Dimensión","Análisis jurídico-normativo") -> 0.44166667 | G5: =200%-F5 -> 1.5583333 | I5: Parte visble | J5: 1
A6: Biofísica y ecológica | B6: 61.3 | C6: 91 | E6: =A6 -> Biofísica y ecológica | F6: =GETPIVOTDATA("Suma de Puntaje para la gobernanza",$A$3,"Dimensión","Biofísica y ecológica")/GETPIVOTDATA("Suma de Puntaje máximo del indicador",$A$3,"Dimensión","Biofísica y ecológica") -> 0.67362637 | G6: =200%-F6 -> 1.3263736 | I6: Parte oculta | J6: 1
A7: Cambio climático y gestión del riesgo | B7: 49 | C7: 134 | E7: =A7 -> Cambio climático y gestión del riesgo | F7: =GETPIVOTDATA("Suma de Puntaje para la gobernanza",$A$3,"Dimensión","Cambio climático y gestión del riesgo ")/GETPIVOTDATA("Suma de Puntaje máximo del indicador",$A$3,"Dimensión","Cambio climático y gestión del riesgo ") -> 0.36567164 | G7: =200%-F7 -> 1.6343284
A8: Económica | B8: 74.5 | C8: 82 | E8: =A8 -> Económica | F8: =GETPIVOTDATA("Suma de Puntaje para la gobernanza",$A$3,"Dimensión","Económica")/GETPIVOTDATA("Suma de Puntaje máximo del indicador",$A$3,"Dimensión","Económica") -> 0.90853659 | G8: =200%-F8 -> 1.0914634
A9: Gestión y evaluación ambiental | B9: 33 | C9: 57 | E9: =A9 -> Gestión y evaluación ambiental | F9: =GETPIVOTDATA("Suma de Puntaje para la gobernanza",$A$3,"Dimensión","Gestión y evaluación ambiental")/GETPIVOTDATA("Suma de Puntaje máximo del indicador",$A$3,"Dimensión","Gestión y evaluación ambiental") -> 0.57894737 | G9: =200%-F9 -> 1.4210526
A10: Social | B10: 77 | C10: 89 | E10: =A10 -> Social | F10: =GETPIVOTDATA("Suma de Puntaje para la gobernanza",$A$3,"Dimensión","Social")/GETPIVOTDATA("Suma de Puntaje máximo del indicador",$A$3,"Dimensión","Social") -> 0.86516854 | G10: =200%-F10 -> 1.1348315
A11: Subsector de energía eléctrica | B11: 62 | C11: 91 | E11: =A11 -> Subsector de energía eléctrica | F11: =GETPIVOTDATA("Suma de Puntaje para la gobernanza",$A$3,"Dimensión","Subsector de energía eléctrica")/GETPIVOTDATA("Suma de Puntaje máximo del indicador",$A$3,"Dimensión","Subsector de energía eléctrica") -> 0.68131868 | G11: =200%-F11 -> 1.3186813
A12: Subsector de hidrocarburos | B12: 48 | C12: 122 | E12: =A12 -> Subsector de hidrocarburos | F12: =GETPIVOTDATA("Suma de Puntaje para la gobernanza",$A$3,"Dimensión","Subsector de hidrocarburos ")/GETPIVOTDATA("Suma de Puntaje máximo del indicador",$A$3,"Dimensión","Subsector de hidrocarburos ") -> 0.39344262 | G12: =200%-F12 -> 1.6065574
A13: Subsector de minería | B13: 33 | C13: 83 | E13: =A13 -> Subsector de minería | F13: =GETPIVOTDATA("Suma de Puntaje para la gobernanza",$A$3,"Dimensión","Subsector de minería ")/GETPIVOTDATA("Suma de Puntaje máximo del indicador",$A$3,"Dimensión","Subsector de minería ") -> 0.39759036 | G13: =200%-F13 -> 1.6024096
A14: Transición energética justa | B14: 64 | C14: 96 | E14: =A14 -> Transición energética justa | F14: =GETPIVOTDATA("Suma de Puntaje para la gobernanza",$A$3,"Dimensión","Transición energética justa")/GETPIVOTDATA("Suma de Puntaje máximo del indicador",$A$3,"Dimensión","Transición energética justa") -> 0.66666667 | G14: =200%-F14 -> 1.3333333
A15: Total general | B15: 571.2 | C15: 1000
A21: Etiquetas de fila | B21: Suma de Puntaje para la gobernanza | C21: Suma de Puntaje máximo del indicador | E21: Objetivos | F21: Porcentaje
A22: Efectividad | B22: 246.8 | C22: 360 | E22: =A22 -> Efectividad | F22: =GETPIVOTDATA("Suma de Puntaje para la gobernanza",$A$21,"Objetivos","Efectividad")/GETPIVOTDATA("Suma de Puntaje máximo del indicador",$A$21,"Objetivos","Efectividad") -> 0.68555556
A23: Equidad | B23: 154.6 | C23: 283 | E23: =A23 -> Equidad | F23: =GETPIVOTDATA("Suma de Puntaje para la gobernanza",$A$21,"Objetivos","Equidad")/GETPIVOTDATA("Suma de Puntaje máximo del indicador",$A$21,"Objetivos","Equidad") -> 0.54628975
A24: Receptividad | B24: 127 | C24: 253 | E24: =A24 -> Receptividad | F24: =GETPIVOTDATA("Suma de Puntaje para la gobernanza",$A$21,"Objetivos","Receptividad")/GETPIVOTDATA("Suma de Puntaje máximo del indicador",$A$21,"Objetivos","Receptividad") -> 0.50197628
A25: Robustez | B25: 42.8 | C25: 104 | E25: =A25 -> Robustez | F25: =GETPIVOTDATA("Suma de Puntaje para la gobernanza",$A$21,"Objetivos","Robustez")/GETPIVOTDATA("Suma de Puntaje máximo del indicador",$A$21,"Objetivos","Robustez") -> 0.41153846
A26: Total general | B26: 571.2 | C26: 1000
A29: Etiquetas de fila | B29: Suma de Puntaje para la gobernanza | C29: Suma de Puntaje máximo del indicador
A30: Anticipación | B30: 55 | C30: 131
A31: Capacidad - Capacidad institucional | B31: 6 | C31: 21
A32: Capacidad - Capacidad institucional para actuar | B32: 1 | C32: 14
A33: Coordinación, dirección, capacidad y eficiencia | B33: 25 | C33: 40
A34: Eficiencia | B34: 185.8 | C34: 240
A35: Flexibilidad y Adaptación | B35: 72 | C35: 122
A36: Información | B36: 13 | C36: 42
A37: Información | B37: 6 | C37: 21
A38: Justicia | B38: 47 | C38: 103
A39: Legitimidad | B39: 10.8 | C39: 35
A40: Legitimidad - Cumplimiento legal | B40: 26 | C40: 48
A41: Participación | B41: 24 | C41: 24
... A48: Total general | B48: 571.2 | C48: 1000
A50: Etiquetas de fila | B50: Suma de Porcentaje alcanzado | E50: Indicador | F50: Porcentaje
A51: Análisis institucional | B51: 131.57895
A52: Acceso a justicia | B52: 10.526316 | E52: =A52 -> Acceso a justicia | F52: =GETPIVOTDATA("Porcentaje alcanzado",$A$50,"Dimensión","Análisis institucional","Índice / Indicador","Acceso a justicia") -> 10.526316
A53: Coordinación intersectorial | B53: 21.052632 | E53: =A53 -> Coordinación intersectorial | F53: =GETPIVOTDATA("Porcentaje alcanzado",$A$50,"Dimensión","Análisis institucional","Índice / Indicador","Coordinación intersectorial") -> 21.052632
A54: Puntaje del sector de minas y energía en el índice de Desempeño Institucional | B54: 100 | E54: =A54 -> Puntaje del sector de minas y energía en el índice de Desempeño Institucional | F54: =GETPIVOTDATA("Porcentaje alcanzado",$A$50,"Dimensión","Análisis institucional","Índice / Indicador","Puntaje del sector de minas y energía en el índice de Desempeño Institucional") -> 100
A55: Análisis jurídico-normativo | B55: 219.07268
A56: Análisis de impacto regulatorio con dimensión ambiental | B56: 72.857143 | E56: =A56 -> Análisis de impacto regulatorio con dimensión ambiental | F56: =GETPIVOTDATA("Porcentaje alcanzado",$A$50,"Dimensión","Análisis jurídico-normativo","Índice / Indicador","Análisis de impacto regulatorio con dimensión ambiental") -> 72.857143
A57: Contexto favorable para el ejercicio de los derechos ambientales | B57: 50 | E57: =A57 -> Contexto favorable para el ejercicio de los derechos ambientales | F57: =GETPIVOTDATA("Porcentaje alcanzado",$A$50,"Dimensión","Análisis jurídico-normativo","Índice / Indicador","Contexto favorable para el ejercicio de los derechos ambientales") -> 50
A58: Evaluación ex post de regulaciones | B58: 5.2631579 | E58: =A58 -> Evaluación ex post de regulaciones | F58: =GETPIVOTDATA("Porcentaje alcanzado",$A$50,"Dimensión","Análisis jurídico-normativo","Índice / Indicador","Evaluación ex post de regulaciones") -> 5.2631579
A59: Procesos de consulta pública en la producción normativa | B59: 72.857143 | E59: =A59 -> Procesos de consulta pública en la producción normativa | F59: =GETPIVOTDATA("Porcentaje alcanzado",$A$50,"Dimensión","Análisis jurídico-normativo","Índice / Indicador","Procesos de consulta pública en la producción normativa") -> 72.857143
A60: Reconocimiento y protección de los derechos ambientales en la política sectorial de derechos humanos | B60: 18.095238 | E60: =A60 -> Reconocimiento y protección de los derechos ambientales en la política sectorial de derechos humanos | F60: =GETPIVOTDATA("Porcentaje alcanzado",$A$50,"Dimensión","Análisis jurídico-normativo","Índice / Indicador","Reconocimiento y protección de los derechos ambientales en la política sectorial de derechos humanos") -> 18.095238
A61: Biofísica y ecológica | B61: 343.68421
A62: Área de superposición de cada subsector minero energético con áreas prioritarias de conservación | B62: 43.684211 | E62: =A62 -> Área de superposición de cada subsector minero energético con áreas prioritarias de conservación | F62: =GETPIVOTDATA("Porcentaje alcanzado",$A$50,"Dimensión","Biofísica y ecológica","Índice / Indicador","Área de superposición de cada subsector minero energético con áreas prioritarias de conservación") -> 43.684211
A63: Área de superposición de cada subsector minero energético con determinantes ambientales | B63: 50 | E63: =A63 -> Área de superposición de cada subsector minero energético con determinantes ambientales | F63: =GETPIVOTDATA("Porcentaje alcanzado",$A$50,"Dimensión","Biofísica y ecológica","Índice / Indicador","Área de superposición de cada subsector minero energético con determinantes ambientales") -> 50
A64: Variación de la demanda hídrica | B64: 100 | E64: =A64 -> Variación de la demanda hídrica | F64: =GETPIVOTDATA("Porcentaje alcanzado",$A$50,"Dimensión","Biofísica y ecológica","Índice / Indicador","Variación de la demanda hídrica") -> 100
A65: Variación de la huella hídrica azul | B65: 100 | E65: =A65 -> Variación de la huella hídrica azul | F65: =GETPIVOTDATA("Porcentaje alcanzado",$A$50,"Dimensión","Biofísica y ecológica","Índice / Indicador","Variación de la huella hídrica azul") -> 100
A66: Variación del área compensada por cada subsector minero energético | B66: 50 | E66: =A66 -> Variación del área compensada por cada subsector minero energético | F66: =GETPIVOTDATA("Porcentaje alcanzado",$A$50,"Dimensión","Biofísica y ecológica","Índice / Indicador","Variación del área compensada por cada subsector minero energético") -> 50
A67: Cambio climático y gestión del riesgo | B67: 210.38961
A68: Índice de Derrames de Hidrocarburos (IDH) | B68: 50
A69: Índice de Gravedad de Accidentes Mineros (IGAM) | B69: 25
A70: índice de Severidad de Accidentes Eléctricos (ISAE) | B70: 75
A71: Índice de vulnerabilidad climática | B71: 0
A72: Tasa de variación de financiamiento climático | B72: 28.571429
A73: Variación de emisiones de GEI del sector | B73: 31.818182
A74: Económica | B74: 431.81818
A75: Participación del sector minero energético en el PIB nacional | B75: 100
A76: Participación del sector minero energético en las exportaciones del país | B76: 31.818182
A77: Recaudo efectivo de regalías | B77: 100
A78: Regalías destinadas al sector ambiente y desarrollo sostenible | B78: 100
... A113: Total general | B113: 2917.3168

Sheet Resultado
A1: N° | B1: Dimensión | C1: Objetivos | D1: Atributo | E1: Índice / Indicador | F1: Resultado del indicador (en sus unidades) | G1: Puntaje para la gobernanza | H1: Puntaje máximo del indicador | I1: Porcentaje alcanzado | J1: Columna1
A2: 1 | B2: Análisis jurídico-normativo | C2: Robustez | D2: Legitimidad | E2: Reconocimiento y protección de los derechos ambientales en la política sectorial de derechos humanos | F2: ='Puntaje asignado indicador'!D3 -> 7.75 | G2: ='Puntaje asignado indicador'!G3 -> 7.75 | H2: =Tabla1[[#This Row],[Aproximación a la unidad]] -> 21 | I2: =G2/H2*100 -> 36.904762
A3: 2 | B3: Análisis jurídico-normativo | C3: Robustez | D3: Legitimidad | E3: Contexto favorable para el ejercicio de los derechos ambientales | F3: ='Puntaje asignado indicador'!D4 -> 2.8 | G3: ='Puntaje asignado indicador'!G4 -> 2.8 | H3: =Tabla1[[#This Row],[Aproximación a la unidad]] -> 14 | I3: =G3/H3*100 -> 20
A4: 3 | B4: Análisis jurídico-normativo | C4: Equidad | D4: Reconocimiento, Participación, Transparencia | E4: Análisis de impacto regulatorio con dimensión ambiental | F4: ='Puntaje asignado indicador'!D5 -> 15.3 | G4: ='Puntaje asignado indicador'!G5 -> 15.3 | H4: =Tabla1[[#This Row],[Aproximación a la unidad]] -> 21 | I4: =G4/H4*100 -> 72.857143
A5: 4 | B5: Análisis jurídico-normativo | C5: Equidad | D5: Reconocimiento, Participación, Transparencia | E5: Evaluación ex post de regulaciones | F5: ='Puntaje asignado indicador'!D6 -> 1 | G5: ='Puntaje asignado indicador'!G6 -> 1 | H5: =Tabla1[[#This Row],[Aproximación a la unidad]] -> 19 | I5: =G5/H5*100 -> 5.2631579
A6: 5 | B6: Análisis jurídico-normativo | C6: Equidad | D6: Reconocimiento, Participación, Transparencia | E6: Procesos de consulta pública en la producción normativa | F6: 15.3 | G6: ='Puntaje asignado indicador'!G7 -> 15.3 | H6: =Tabla1[[#This Row],[Aproximación a la unidad]] -> 21 | I6: =G6/H6*100 -> 72.857143
A7: 6 | B7: Análisis institucional | C7: Efectividad | D7: Coordinación, dirección, capacidad y eficiencia | E7: Puntaje del sector de minas y energía en el índice de Desempeño Institucional | F7: ='Puntaje asignado indicador'!D8 -> 4.2 | G7: ='Puntaje asignado indicador'!G8 -> 4.2 | H7: =Tabla1[[#This Row],[Aproximación a la unidad]] -> 21 | I7: =G7/H7*100 -> 20
A8: 7 | B8: Análisis institucional | C8: Efectividad | D8: Coordinación, dirección, capacidad y eficiencia | E8: Coordinación intersectorial | F8: ='Puntaje asignado indicador'!D9 -> 4 | G8: ='Puntaje asignado indicador'!G9 -> 4 | H8: =Tabla1[[#This Row],[Aproximación a la unidad]] -> 19 | I8: =G8/H8*100 -> 21.052632
A9: 8 | B9: Análisis institucional | C9: Equidad | D9: Reconocimiento y justicia | E9: Acceso a justicia | F9: ='Puntaje asignado indicador'!D10 -> 2 | G9: ='Puntaje asignado indicador'!G10 -> 2 | H9: =Tabla1[[#This Row],[Aproximación a la unidad]] -> 19 | I9: =G9/H9*100 -> 10.526316
A10: 9 | B10: Social | C10: Equidad | D10: Participación | E10: Participación ciudadana | F10: ='Puntaje asignado indicador'!D11 -> 84.899371 | G10: ='Puntaje asignado indicador'!G11 -> 19 | H10: =Tabla1[[#This Row],[Aproximación a la unidad]] -> 24 | I10: =G10/H10*100 -> 79.166667
A11: 10 | B11: Social | C11: Equidad | D11: Reconocimiento | E11: Interacción de género y enfoque diferencial | F11: ='Puntaje asignado indicador'!D12 -> 27.625029 | G11: ='Puntaje asignado indicador'!G12 -> 15 | H11: =Tabla1[[#This Row],[Aproximación a la unidad]] -> 19 | I11: =G11/H11*100 -> 78.947368
A12: 11 | B12: Social | C12: Equidad | D12: Justicia | E12: Conflictividad socioambiental | F12: ='Puntaje asignado indicador'!D13 -> 35.251799 | G12: ='Puntaje asignado indicador'!G13 -> 18 | H12: =Tabla1[[#This Row],[Aproximación a la unidad]] -> 24 | I12: =G12/H12*100 -> 75
A13: 12 | B13: Social | C13: Equidad | D13: Transparencia | E13: Cumplimiento a PQRSD | F13: ='Puntaje asignado indicador'!D14 -> 94.3125 | G13: ='Puntaje asignado indicador'!G14 -> 16 | H13: =Tabla1[[#This Row],[Aproximación a la unidad]] -> 22 | I13: =G13/H13*100 -> 72.727273
A14: 13 | B14: Biofísica y ecológica | C14: Efectividad | D14: Eficiencia | E14: Variación de la demanda hídrica | F14: ='Puntaje asignado indicador'!D15 -> 1507.5 | G14: ='Puntaje asignado indicador'!G15 -> 17 | H14: =Tabla1[[#This Row],[Aproximación a la unidad]] -> 17 | I14: =G14/H14*100 -> 100
A15: 14 | B15: Biofísica y ecológica | C15: Efectividad | D15: Eficiencia | E15: Variación de la huella hídrica azul | F15: ='Puntaje asignado indicador'!D16 -> 39.6 | G15: ='Puntaje asignado indicador'!G16 -> 17 | H15: =Tabla1[[#This Row],[Aproximación a la unidad]] -> 17 | I15: =G15/H15*100 -> 100
A16: 15 | B16: Biofísica y ecológica | C16: Efectividad | D16: Eficiencia | E16: Variación del área compensada por cada subsector minero energético | F16: ='Puntaje asignado indicador'!D17 -> 2975.8631 | G16: ='Puntaje asignado indicador'!G17 -> 9.5 | H16: =Tabla1[[#This Row],[Aproximación a la unidad]] -> 19 | I16: =G16/H16*100 -> 50
A17: 16 | B17: Biofísica y ecológica | C17: Efectividad | D17: Eficiencia | E17: Área de superposición de cada subsector minero energético con determinantes ambientales | F17: ='Puntaje asignado indicador'!D18 -> 43.950026 | G17: ='Puntaje asignado indicador'!G18 -> 14.25 | H17: =Tabla1[[#This Row],[Aproximación a la unidad]] -> 19 | I17: =G17/H17*100 -> 75
A18: 17 | B18: Biofísica y ecológica | C18: Efectividad | D18: Eficiencia | E18: Área de superposición de cada subsector minero energético con áreas prioritarias de conservación | F18: ='Puntaje asignado indicador'!D19 -> 34.475552 | G18: ='Puntaje asignado indicador'!G19 -> 10 | H18: =Tabla1[[#This Row],[Aproximación a la unidad]] -> 19 | I18: =G18/H18*100 -> 52.631579
... A52: 51 | B52: Subsector de energía eléctrica | C52: Equidad | D52: Participación – Acceso a la Información | E52: Porcentaje de Informes de Sostenibilidad anuales publicados por empresas generadoras del país. | F52: ='Puntaje asignado indicador'!D53 -> 54.545455 | G52: ='Puntaje asignado indicador'!G53 -> 14 | H52: =Tabla1[[#This Row],[Aproximación a la unidad]] -> 21 | I52: =G52/H52*100 -> 66.666667
G54: =SUBTOTAL(109,Tabla2[Puntaje para la gobernanza]) -> 556.6 | H54: =SUBTOTAL(109,Tabla2[Puntaje máximo del indicador]) -> 1000 | I54: =SUBTOTAL(101,Tabla2[Porcentaje alcanzado]) -> 55.559415
G56: =Tabla2[[#Totals],[Puntaje para la gobernanza]]/Tabla2[[#Totals],[Puntaje máximo del indicador]] -> 0.5566

Sheet tablas dinamicas
A1: Etiquetas de fila | B1: Promedio de Porcentaje alcanzado
A2: Análisis institucional | B2: 43.859649 | C2: =IF(B2>=80,"Verde (≥80%) – gobernanza ambiental sólida", IF(B2>=40,"Amarillo (40–79%) – gobernanza intermedia con brechas por superar", "Rojo (<40%) – gobernanza débil, con alto riesgo socioambiental")) -> Amarillo (40–79%) – gobernanza intermedia con brechas por superar
A3: Análisis jurídico-normativo | B3: 43.814536 | C3: =IF(B3>=80,"Verde (≥80%) – gobernanza ambiental sólida", IF(B3>=40,"Amarillo (40–79%) – gobernanza intermedia con brechas por superar", "Rojo (<40%) – gobernanza débil, con alto riesgo socioambiental")) -> Amarillo (40–79%) – gobernanza intermedia con brechas por superar
A4: Biofísica y ecológica | B4: 68.736842 | C4: =IF(B4>=80,"Verde (≥80%) – gobernanza ambiental sólida", IF(B4>=40,"Amarillo (40–79%) – gobernanza intermedia con brechas por superar", "Rojo (<40%) – gobernanza débil, con alto riesgo socioambiental")) -> Amarillo (40–79%) – gobernanza intermedia con brechas por superar
A5: Cambio climático y gestión del riesgo | B5: 35.064935 | C5: =IF(B5>=80,"Verde (≥80%) – gobernanza ambiental sólida", IF(B5>=40,"Amarillo (40–79%) – gobernanza intermedia con brechas por superar", "Rojo (<40%) – gobernanza débil, con alto riesgo socioambiental")) -> Rojo (<40%) – gobernanza débil, con alto riesgo socioambiental
A6: Económica | B6: 86.363636 | C6: =IF(B6>=80,"Verde (≥80%) – gobernanza ambiental sólida", IF(B6>=40,"Amarillo (40–79%) – gobernanza intermedia con brechas por superar", "Rojo (<40%) – gobernanza débil, con alto riesgo socioambiental")) -> Verde (≥80%) – gobernanza ambiental sólida
A7: Gestión y evaluación ambiental | B7: 60.735171 | C7: =IF(B7>=80,"Verde (≥80%) – gobernanza ambiental sólida", IF(B7>=40,"Amarillo (40–79%) – gobernanza intermedia con brechas por superar", "Rojo (<40%) – gobernanza débil, con alto riesgo socioambiental")) -> Amarillo (40–79%) – gobernanza intermedia con brechas por superar
A8: Social | B8: 86.931818 | C8: =IF(B8>=80,"Verde (≥80%) – gobernanza ambiental sólida", IF(B8>=40,"Amarillo (40–79%) – gobernanza intermedia con brechas por superar", "Rojo (<40%) – gobernanza débil, con alto riesgo socioambiental")) -> Verde (≥80%) – gobernanza ambiental sólida
A9: Subsector de energía eléctrica | B9: 68.75 | C9: =IF(B9>=80,"Verde (≥80%) – gobernanza ambiental sólida", IF(B9>=40,"Amarillo (40–79%) – gobernanza intermedia con brechas por superar", "Rojo (<40%) – gobernanza débil, con alto riesgo socioambiental")) -> Amarillo (40–79%) – gobernanza intermedia con brechas por superar
A10: Subsector de hidrocarburos | B10: 40.873016 | C10: =IF(B10>=80,"Verde (≥80%) – gobernanza ambiental sólida", IF(B10>=40,"Amarillo (40–79%) – gobernanza intermedia con brechas por superar", "Rojo (<40%) – gobernanza débil, con alto riesgo socioambiental")) -> Amarillo (40–79%) – gobernanza intermedia con brechas por superar
A11: Subsector de minería | B11: 36.011905 | C11: =IF(B11>=80,"Verde (≥80%) – gobernanza ambiental sólida", IF(B11>=40,"Amarillo (40–79%) – gobernanza intermedia con brechas por superar", "Rojo (<40%) – gobernanza débil, con alto riesgo socioambiental")) -> Rojo (<40%) – gobernanza débil, con alto riesgo socioambiental
A12: Transición energética justa | B12: 64.42577 | C12: =IF(B12>=80,"Verde (≥80%) – gobernanza ambiental sólida", IF(B12>=40,"Amarillo (40–79%) – gobernanza intermedia con brechas por superar", "Rojo (<40%) – gobernanza débil, con alto riesgo socioambiental")) -> Amarillo (40–79%) – gobernanza intermedia con brechas por superar
A13: Total general | B13: 57.202289
A17: Dimensión | B17: Análisis institucional
A19: Etiquetas de fila | B19: Promedio de Porcentaje alcanzado
A20: Efectividad | B20: 60.526316
A21: Equidad | B21: 10.526316
A22: Total general | B22: 43.859649
A29: Etiquetas de fila | B29: Promedio de Porcentaje alcanzado
A30: Anticipación | B30: 41.081871
A31: Capacidad - Capacidad institucional | B31: 28.571429
A32: Capacidad - Capacidad institucional para actuar | B32: 7.1428571
A33: Coordinación, dirección, capacidad y eficiencia | B33: 60.526316
A34: Eficiencia | B34: 76.503847
A35: Flexibilidad y Adaptación | B35: 59.647495
A36: Información | B36: 30.952381
A37: Información | B37: 28.571429
A38: Justicia | B38: 46.834734
A39: Legitimidad | B39: 34.047619
A40: Legitimidad - Cumplimiento legal | B40: 54.166667
A41: Participación | B41: 100
... A48: Total general | B48: 57.202289
